Workbook

Sheet README
A1: CRITICAL SUPPLIER PERFORMANCE REVIEW — REVAMPED WORKBOOK
A2: Remediation & Restructuring Q1 2026 → Template Reusable untuk Q2 2026
A4: 1. APA YANG BERUBAH DARI FILE ASLI
A5: • 18 sheet per-supplier (ITSEC, IPROTEKSI, dst) dengan angka HARDCODE dikonsolidasikan menjadi 1 sheet SCORE CALC — semua nilai sekarang formula, ditarik LANGSUNG dari RAW DATA, tidak ada lagi copy-paste manual.
A6: • Sheet CONFIG baru ditambahkan: berisi mapping kolom (Quality/Timeline/Relationship) per supplier ke RAW DATA. Ini yang membuat file REUSABLE — untuk Q2, cukup update kolom 'Raw Sheet Name' di CONFIG dan tempel data baru, seluruh perhitungan otomatis mengikuti.
A7: • Sheet RESULT dirombak: Total Score, Status, Remarks, dan DD Result (by User) sekarang 100% formula (live link ke raw data). Kolom 'Assessment Result (by SRM)' dan 'Repetition of Below Expectation' tetap manual input (kuning) karena butuh judgement SRM, bukan hasil kalkulasi.
A8: • Sheet SUMMARY diperbaiki: '% Vendor Dievaluasi' sebelumnya menampilkan angka mentah (1) alih-alih persentase — sekarang benar (0%-100%) dan berbasis formula, bukan hitung manual.
A9: • Sheet HISTORICAL: kolom skor Q1 2026 sekarang live-link ke RESULT (bukan angka mati), dan status (Meet/Exceed/dst) memakai formula ambang batas yang SAMA dengan kolom tahun-tahun sebelumnya (sebelumnya kolom Q1 2026 di-ketik manual, tidak konsisten dengan formula tahun lalu).
A10: • Sheet 'Sheet1' (draft yang tidak terpakai, cuma 1 baris) dihapus.
A12: 2. BUG YANG DITEMUKAN & DIPERBAIKI (PENTING)
A13: Saat formula lama diganti dengan link otomatis ke raw data, ditemukan 3 kesalahan formula di file asli:
A14: a) Satria Antaran Prima – Mailing Room: formula Timeline ("=AVERAGE(I3:P3)*35%") salah rentang — ikut merata-ratakan kolom Quality & hasil weighted Quality (M3) alih-alih hanya kolom Timeline (N:P). Total Score resmi 3.063272 → seharusnya 3.404167. Status TETAP 'Meet Expectation', tidak berubah.
... A39: Score <= 1.9 → Unsatisfactory

Sheet CONFIG
A1: No | B1: Supplier & Service (Key) | C1: PIC Email | D1: Raw Sheet Name (Quarter Aktif) | E1: Quality Col Start | F1: Quality Col End | G1: Timeline Col Start | H1: Timeline Col End | I1: Relationship Col Start | J1: Relationship Col End | K1: Remarks Col | L1: Financial Assessment Col | M1: Reputational Col | N1: DPIA Required Col | O1: DPSQ Required Col | P1: VSDDT Required Col | Q1: Action Plan Col
A2: 1 | B2: Itsec Asia - Penetration Testing | C2: fauzi.aryanto@axa-mandiri.co.id | D2: RAW DATA Q1 - 1 | E2: FJ | F2: FL | G2: FN | H2: FP | I2: GH | J2: GJ | K2: GS | L2: GK | M2: GL | N2: GM | O2: GN | P2: GO | Q2: GQ
A3: 2 | B3: Iproteksi Telematika - Penetration Testing | C3: fauzi.aryanto@axa-mandiri.co.id | D3: RAW DATA Q1 - 1 | E3: FG | F3: FI | G3: FN | H3: FP | I3: GH | J3: GJ | K3: GS | L3: GK | M3: GL | N3: GM | O3: GN | P3: GO | Q3: GQ
A4: 3 | B4: FPT Metrodata - Penetration Testing | C4: fauzi.aryanto@axa-mandiri.co.id | D4: RAW DATA Q1 - 1 | E4: FD | F4: FF | G4: FN | H4: FP | I4: GH | J4: GJ | K4: GS | L4: GK | M4: GL | N4: GM | O4: GN | P4: GO | Q4: GQ
A5: 4 | B5: Satria Antaran Prima - Mailing Room | C5: ibnu.kumala@axa-mandiri.co.id | D5: RAW DATA Q1 - 1 | E5: DX | F5: EE | G5: FN | H5: FP | I5: GH | J5: GJ | K5: GS | L5: GK | M5: GL | N5: GM | O5: GN | P5: GO | Q5: GQ
A6: 5 | B6: Informasi Teknologi Indonesia - SMS Broadcast | C6: fifin.sarinurlita@axa-mandiri.co.id | D6: RAW DATA Q1 - 1 | E6: AA | F6: AK | G6: FO | H6: FS | I6: GH | J6: GJ | K6: GS | L6: GK | M6: GL | N6: GM | O6: GN | P6: GO | Q6: GQ
A7: 6 | B7: Satria Antaran Prima - Courier Service | C7: fifin.sarinurlita@axa-mandiri.co.id | D7: RAW DATA Q1 - 1 | E7: DI | F7: DW | G7: GE | H7: GG | I7: GH | J7: GJ | K7: GS | L7: GK | M7: GL | N7: GM | O7: GN | P7: GO | Q7: GQ
A8: 7 | B8: Multifiling Mitra Indonesia - Record Management Service | C8: ibnu.kumala@axa-mandiri.co.id | D8: RAW DATA Q1 - 1 | E8: AY | F8: BI | G8: FU | H8: FX | I8: GH | J8: GJ | K8: GS | L8: GK | M8: GL | N8: GM | O8: GN | P8: GO | Q8: GQ
A9: 8 | B9: Indosat - Layanan PBX berbasiskan cloud dengan Teknologi SIP Trunk | C9: nuril.hudha@axa-mandiri.co.id | D9: RAW DATA Q1 - 1 | E9: G | F9: Z | G9: FN | H9: FP | I9: GH | J9: GJ | K9: GS | L9: GK | M9: GL | N9: GM | O9: GN | P9: GO | Q9: GQ
A10: 9 | B10: Ciptadra Softindo - Pemeliharaan Axits & DMTM | C10: raninta.mahardi@axa-mandiri.co.id | D10: RAW DATA Q1 - 1 | E10: BJ | F10: BW | G10: FY | H10: GD | I10: GH | J10: GJ | K10: GS | L10: GK | M10: GL | N10: GM | O10: GN | P10: GO | Q10: GQ
A11: 10 | B11: Target Sukses Sinergi - Email Marketing Automation | C11: bella.depari@axa-mandiri.co.id | D11: RAW DATA Q1 - 1 | E11: EF | F11: EL | G11: FN | H11: FP | I11: GH | J11: GJ | K11: GS | L11: GK | M11: GL | N11: GM | O11: GN | P11: GO | Q11: GQ
A12: 11 | B12: Inmotion Inovasi Teknologi - Jasa Aplikasi Chatbot dan Live Chat | C12: djoko.djoko@axa-mandiri.co.id | D12: RAW DATA Q1 - 1 | E12: BX | F12: DH | G12: FN | H12: FP | I12: GH | J12: GJ | K12: GS | L12: GK | M12: GL | N12: GM | O12: GN | P12: GO | Q12: GQ
A13: 12 | B13: Mitra Integrasi Informatika - SFDC Maintenance | C13: chandra.putra@axa-mandiri.co.id | D13: RAW DATA Q1 - 1 | E13: AL | F13: AX | G13: FN | H13: FP | I13: GH | J13: GJ | K13: GS | L13: GK | M13: GL | N13: GM | O13: GN | P13: GO | Q13: GQ
... A19: 18 | B19: Karya Putra Surya Gemilang - Telemarketing Revamp Project | C19: reza.resdilana@axa-mandiri.co.id | D19: RAW DATA Q1 - 2 | E19: O | F19: Y | G19: CJ | H19: CL | I19: CS | J19: CU | K19: DF | L19: CV | M19: CW | N19: CX | O19: CZ | P19: DB | Q19: DD

Sheet SCORE CALC
A1: No | B1: Supplier & Service | C1: Match Row (helper) | D1: Quality Avg (35%) | E1: Timeline Avg (35%) | F1: Relationship Avg (30%) | G1: TOTAL SCORE | H1: STATUS
A2: =CONFIG!A2 -> 1 | B2: =CONFIG!B2 -> Itsec Asia - Penetration Testing | C2: =MATCH($B2,INDIRECT("'"&CONFIG!D2&"'!$F:$F"),0) -> 2 | D2: =AVERAGE(INDIRECT("'"&CONFIG!D2&"'!"&CONFIG!E2&$C2&":"&CONFIG!F2&$C2)) -> 3 | E2: =AVERAGE(INDIRECT("'"&CONFIG!D2&"'!"&CONFIG!G2&$C2&":"&CONFIG!H2&$C2)) -> 3 | F2: =AVERAGE(INDIRECT("'"&CONFIG!D2&"'!"&CONFIG!I2&$C2&":"&CONFIG!J2&$C2)) -> 3 | G2: =D2*0.35+E2*0.35+F2*0.3 -> 3 | H2: =IF(G2>4.99,"Exceptional",IF(G2>3.99,"Exceed Expectation",IF(G2>=2.99,"Meet Expectation",IF(G2>1.9,"Below Expectation","Unsatisfactory")))) -> Meet Expectation
A3: =CONFIG!A3 -> 2 | B3: =CONFIG!B3 -> Iproteksi Telematika - Penetration Testing | C3: =MATCH($B3,INDIRECT("'"&CONFIG!D3&"'!$F:$F"),0) -> 3 | D3: =AVERAGE(INDIRECT("'"&CONFIG!D3&"'!"&CONFIG!E3&$C3&":"&CONFIG!F3&$C3)) -> 4 | E3: =AVERAGE(INDIRECT("'"&CONFIG!D3&"'!"&CONFIG!G3&$C3&":"&CONFIG!H3&$C3)) -> 4 | F3: =AVERAGE(INDIRECT("'"&CONFIG!D3&"'!"&CONFIG!I3&$C3&":"&CONFIG!J3&$C3)) -> 4 | G3: =D3*0.35+E3*0.35+F3*0.3 -> 4 | H3: =IF(G3>4.99,"Exceptional",IF(G3>3.99,"Exceed Expectation",IF(G3>=2.99,"Meet Expectation",IF(G3>1.9,"Below Expectation","Unsatisfactory")))) -> Exceed Expectation
A4: =CONFIG!A4 -> 3 | B4: =CONFIG!B4 -> FPT Metrodata - Penetration Testing | C4: =MATCH($B4,INDIRECT("'"&CONFIG!D4&"'!$F:$F"),0) -> 4 | D4: =AVERAGE(INDIRECT("'"&CONFIG!D4&"'!"&CONFIG!E4&$C4&":"&CONFIG!F4&$C4)) -> 3 | E4: =AVERAGE(INDIRECT("'"&CONFIG!D4&"'!"&CONFIG!G4&$C4&":"&CONFIG!H4&$C4)) -> 3 | F4: =AVERAGE(INDIRECT("'"&CONFIG!D4&"'!"&CONFIG!I4&$C4&":"&CONFIG!J4&$C4)) -> 3 | G4: =D4*0.35+E4*0.35+F4*0.3 -> 3 | H4: =IF(G4>4.99,"Exceptional",IF(G4>3.99,"Exceed Expectation",IF(G4>=2.99,"Meet Expectation",IF(G4>1.9,"Below Expectation","Unsatisfactory")))) -> Meet Expectation
A5: =CONFIG!A5 -> 4 | B5: =CONFIG!B5 -> Satria Antaran Prima - Mailing Room | C5: =MATCH($B5,INDIRECT("'"&CONFIG!D5&"'!$F:$F"),0) -> 5 | D5: =AVERAGE(INDIRECT("'"&CONFIG!D5&"'!"&CONFIG!E5&$C5&":"&CONFIG!F5&$C5)) -> 3.25 | E5: =AVERAGE(INDIRECT("'"&CONFIG!D5&"'!"&CONFIG!G5&$C5&":"&CONFIG!H5&$C5)) -> 3.3333333 | F5: =AVERAGE(INDIRECT("'"&CONFIG!D5&"'!"&CONFIG!I5&$C5&":"&CONFIG!J5&$C5)) -> 3.6666667 | G5: =D5*0.35+E5*0.35+F5*0.3 -> 3.4041667 | H5: =IF(G5>4.99,"Exceptional",IF(G5>3.99,"Exceed Expectation",IF(G5>=2.99,"Meet Expectation",IF(G5>1.9,"Below Expectation","Unsatisfactory")))) -> Meet Expectation
A6: =CONFIG!A6 -> 5 | B6: =CONFIG!B6 -> Informasi Teknologi Indonesia - SMS Broadcast | C6: =MATCH($B6,INDIRECT("'"&CONFIG!D6&"'!$F:$F"),0) -> 6 | D6: =AVERAGE(INDIRECT("'"&CONFIG!D6&"'!"&CONFIG!E6&$C6&":"&CONFIG!F6&$C6)) -> 3 | E6: =AVERAGE(INDIRECT("'"&CONFIG!D6&"'!"&CONFIG!G6&$C6&":"&CONFIG!H6&$C6)) -> 3 | F6: =AVERAGE(INDIRECT("'"&CONFIG!D6&"'!"&CONFIG!I6&$C6&":"&CONFIG!J6&$C6)) -> 3 | G6: =D6*0.35+E6*0.35+F6*0.3 -> 3 | H6: =IF(G6>4.99,"Exceptional",IF(G6>3.99,"Exceed Expectation",IF(G6>=2.99,"Meet Expectation",IF(G6>1.9,"Below Expectation","Unsatisfactory")))) -> Meet Expectation
A7: =CONFIG!A7 -> 6 | B7: =CONFIG!B7 -> Satria Antaran Prima - Courier Service | C7: =MATCH($B7,INDIRECT("'"&CONFIG!D7&"'!$F:$F"),0) -> 7 | D7: =AVERAGE(INDIRECT("'"&CONFIG!D7&"'!"&CONFIG!E7&$C7&":"&CONFIG!F7&$C7)) -> 3 | E7: =AVERAGE(INDIRECT("'"&CONFIG!D7&"'!"&CONFIG!G7&$C7&":"&CONFIG!H7&$C7)) -> 3 | F7: =AVERAGE(INDIRECT("'"&CONFIG!D7&"'!"&CONFIG!I7&$C7&":"&CONFIG!J7&$C7)) -> 3 | G7: =D7*0.35+E7*0.35+F7*0.3 -> 3 | H7: =IF(G7>4.99,"Exceptional",IF(G7>3.99,"Exceed Expectation",IF(G7>=2.99,"Meet Expectation",IF(G7>1.9,"Below Expectation","Unsatisfactory")))) -> Meet Expectation
A8: =CONFIG!A8 -> 7 | B8: =CONFIG!B8 -> Multifiling Mitra Indonesia - Record Management Service | C8: =MATCH($B8,INDIRECT("'"&CONFIG!D8&"'!$F:$F"),0) -> 8 | D8: =AVERAGE(INDIRECT("'"&CONFIG!D8&"'!"&CONFIG!E8&$C8&":"&CONFIG!F8&$C8)) -> 3.0909091 | E8: =AVERAGE(INDIRECT("'"&CONFIG!D8&"'!"&CONFIG!G8&$C8&":"&CONFIG!H8&$C8)) -> 3 | F8: =AVERAGE(INDIRECT("'"&CONFIG!D8&"'!"&CONFIG!I8&$C8&":"&CONFIG!J8&$C8)) -> 3 | G8: =D8*0.35+E8*0.35+F8*0.3 -> 3.0318182 | H8: =IF(G8>4.99,"Exceptional",IF(G8>3.99,"Exceed Expectation",IF(G8>=2.99,"Meet Expectation",IF(G8>1.9,"Below Expectation","Unsatisfactory")))) -> Meet Expectation
A9: =CONFIG!A9 -> 8 | B9: =CONFIG!B9 -> Indosat - Layanan PBX berbasiskan cloud dengan Teknologi SIP Trunk | C9: =MATCH($B9,INDIRECT("'"&CONFIG!D9&"'!$F:$F"),0) -> 9 | D9: =AVERAGE(INDIRECT("'"&CONFIG!D9&"'!"&CONFIG!E9&$C9&":"&CONFIG!F9&$C9)) -> 3.0526316 | E9: =AVERAGE(INDIRECT("'"&CONFIG!D9&"'!"&CONFIG!G9&$C9&":"&CONFIG!H9&$C9)) -> 3 | F9: =AVERAGE(INDIRECT("'"&CONFIG!D9&"'!"&CONFIG!I9&$C9&":"&CONFIG!J9&$C9)) -> 4 | G9: =D9*0.35+E9*0.35+F9*0.3 -> 3.3184211 | H9: =IF(G9>4.99,"Exceptional",IF(G9>3.99,"Exceed Expectation",IF(G9>=2.99,"Meet Expectation",IF(G9>1.9,"Below Expectation","Unsatisfactory")))) -> Meet Expectation
A10: =CONFIG!A10 -> 9 | B10: =CONFIG!B10 -> Ciptadra Softindo - Pemeliharaan Axits & DMTM | C10: =MATCH($B10,INDIRECT("'"&CONFIG!D10&"'!$F:$F"),0) -> 10 | D10: =AVERAGE(INDIRECT("'"&CONFIG!D10&"'!"&CONFIG!E10&$C10&":"&CONFIG!F10&$C10)) -> 4 | E10: =AVERAGE(INDIRECT("'"&CONFIG!D10&"'!"&CONFIG!G10&$C10&":"&CONFIG!H10&$C10)) -> 4 | F10: =AVERAGE(INDIRECT("'"&CONFIG!D10&"'!"&CONFIG!I10&$C10&":"&CONFIG!J10&$C10)) -> 4 | G10: =D10*0.35+E10*0.35+F10*0.3 -> 4 | H10: =IF(G10>4.99,"Exceptional",IF(G10>3.99,"Exceed Expectation",IF(G10>=2.99,"Meet Expectation",IF(G10>1.9,"Below Expectation","Unsatisfactory")))) -> Exceed Expectation
A11: =CONFIG!A11 -> 10 | B11: =CONFIG!B11 -> Target Sukses Sinergi - Email Marketing Automation | C11: =MATCH($B11,INDIRECT("'"&CONFIG!D11&"'!$F:$F"),0) -> 11 | D11: =AVERAGE(INDIRECT("'"&CONFIG!D11&"'!"&CONFIG!E11&$C11&":"&CONFIG!F11&$C11)) -> 3.7142857 | E11: =AVERAGE(INDIRECT("'"&CONFIG!D11&"'!"&CONFIG!G11&$C11&":"&CONFIG!H11&$C11)) -> 4 | F11: =AVERAGE(INDIRECT("'"&CONFIG!D11&"'!"&CONFIG!I11&$C11&":"&CONFIG!J11&$C11)) -> 4 | G11: =D11*0.35+E11*0.35+F11*0.3 -> 3.9 | H11: =IF(G11>4.99,"Exceptional",IF(G11>3.99,"Exceed Expectation",IF(G11>=2.99,"Meet Expectation",IF(G11>1.9,"Below Expectation","Unsatisfactory")))) -> Meet Expectation
A12: =CONFIG!A12 -> 11 | B12: =CONFIG!B12 -> Inmotion Inovasi Teknologi - Jasa Aplikasi Chatbot dan Live Chat | C12: =MATCH($B12,INDIRECT("'"&CONFIG!D12&"'!$F:$F"),0) -> 12 | D12: =AVERAGE(INDIRECT("'"&CONFIG!D12&"'!"&CONFIG!E12&$C12&":"&CONFIG!F12&$C12)) -> 4 | E12: =AVERAGE(INDIRECT("'"&CONFIG!D12&"'!"&CONFIG!G12&$C12&":"&CONFIG!H12&$C12)) -> 4 | F12: =AVERAGE(INDIRECT("'"&CONFIG!D12&"'!"&CONFIG!I12&$C12&":"&CONFIG!J12&$C12)) -> 4 | G12: =D12*0.35+E12*0.35+F12*0.3 -> 4 | H12: =IF(G12>4.99,"Exceptional",IF(G12>3.99,"Exceed Expectation",IF(G12>=2.99,"Meet Expectation",IF(G12>1.9,"Below Expectation","Unsatisfactory")))) -> Exceed Expectation
A13: =CONFIG!A13 -> 12 | B13: =CONFIG!B13 -> Mitra Integrasi Informatika - SFDC Maintenance | C13: =MATCH($B13,INDIRECT("'"&CONFIG!D13&"'!$F:$F"),0) -> 13 | D13: =AVERAGE(INDIRECT("'"&CONFIG!D13&"'!"&CONFIG!E13&$C13&":"&CONFIG!F13&$C13)) -> 4.8461538 | E13: =AVERAGE(INDIRECT("'"&CONFIG!D13&"'!"&CONFIG!G13&$C13&":"&CONFIG!H13&$C13)) -> 4.6666667 | F13: =AVERAGE(INDIRECT("'"&CONFIG!D13&"'!"&CONFIG!I13&$C13&":"&CONFIG!J13&$C13)) -> 5 | G13: =D13*0.35+E13*0.35+F13*0.3 -> 4.8294872 | H13: =IF(G13>4.99,"Exceptional",IF(G13>3.99,"Exceed Expectation",IF(G13>=2.99,"Meet Expectation",IF(G13>1.9,"Below Expectation","Unsatisfactory")))) -> Exceed Expectation
... A19: =CONFIG!A19 -> 18 | B19: =CONFIG!B19 -> Karya Putra Surya Gemilang - Telemarketing Revamp Project | C19: =MATCH($B19,INDIRECT("'"&CONFIG!D19&"'!$F:$F"),0) -> 7 | D19: =AVERAGE(INDIRECT("'"&CONFIG!D19&"'!"&CONFIG!E19&$C19&":"&CONFIG!F19&$C19)) -> 3.0909091 | E19: =AVERAGE(INDIRECT("'"&CONFIG!D19&"'!"&CONFIG!G19&$C19&":"&CONFIG!H19&$C19)) -> 3 | F19: =AVERAGE(INDIRECT("'"&CONFIG!D19&"'!"&CONFIG!I19&$C19&":"&CONFIG!J19&$C19)) -> 3 | G19: =D19*0.35+E19*0.35+F19*0.3 -> 3.0318182 | H19: =IF(G19>4.99,"Exceptional",IF(G19>3.99,"Exceed Expectation",IF(G19>=2.99,"Meet Expectation",IF(G19>1.9,"Below Expectation","Unsatisfactory")))) -> Meet Expectation

Sheet RESULT
A1: No | B1: Supplier Name | C1: Service | D1: PIC (User) | E1: Total Score | F1: Status | G1: Remarks (dari User) | H1: DD Result (by User) - Auto | I1: Assessment Result (by SRM) - Manual Input | J1: Repetition Below Expectation - Manual Input | K1: Helper: Below Expectation/Unsatisfactory Name
A2: ='SCORE CALC'!A2 -> 1 | B2: =TRIM(LEFT(CONFIG!B2,FIND(" - ",CONFIG!B2)-1)) -> Itsec Asia | C2: =TRIM(MID(CONFIG!B2,FIND(" - ",CONFIG!B2)+3,255)) -> Penetration Testing | D2: =CONFIG!C2 -> fauzi.aryanto@axa-mandiri.co.id | E2: ='SCORE CALC'!G2 -> 3 | F2: ='SCORE CALC'!H2 -> Meet Expectation | G2: =INDIRECT("'"&CONFIG!D2&"'!"&CONFIG!K2&'SCORE CALC'!C2) -> Currently no need improvement | H2: ="Financial Assessment: "&INDIRECT("'"&CONFIG!D2&"'!"&CONFIG!L2&'SCORE CALC'!C2)&CHAR(10)&"Reputational Assessment: "&INDIRECT("'"&CONFIG!D2&"'!"&CONFIG!M2&'SCORE CALC'!C2)&CHAR(10)&"DPIA: "&INDIRECT("'"&CONFIG!D2&"'!"&CONFIG!N2&'SCORE CALC'!C2)&CHAR(10)&"DPSQ: "&INDIRECT("'"&CONFIG!D2&"'!"&CONFIG!O2&'SCORE CALC'!C2)&CHAR(10)&"VSDDT: "&INDIRECT("'"&CONFIG!D2&"'!"&CONFIG!P2&'SCORE CALC'!C2)&CHAR(10)&"Action Plan: "&INDIRECT("'"&CONFIG!D2&"'!"&CONFIG!Q2&'SCORE CALC'!C2) -> Financial Assessment: Yes Reputational Assessment: Yes DPIA: Not required – DPIA is not applicable for this service DPSQ: Not required – DPSQ is not applicable for this service VSDDT: Required – VSDDT completed and approved Action Plan: Yes – All action items have been completed and coordinated with relevant SME | K2: =IF(OR(F2="Below Expectation",F2="Unsatisfactory"),B2&" - "&C2,"")
A3: ='SCORE CALC'!A3 -> 2 | B3: =TRIM(LEFT(CONFIG!B3,FIND(" - ",CONFIG!B3)-1)) -> Iproteksi Telematika | C3: =TRIM(MID(CONFIG!B3,FIND(" - ",CONFIG!B3)+3,255)) -> Penetration Testing | D3: =CONFIG!C3 -> fauzi.aryanto@axa-mandiri.co.id | E3: ='SCORE CALC'!G3 -> 4 | F3: ='SCORE CALC'!H3 -> Exceed Expectation | G3: =INDIRECT("'"&CONFIG!D3&"'!"&CONFIG!K3&'SCORE CALC'!C3) -> no need improvement | H3: ="Financial Assessment: "&INDIRECT("'"&CONFIG!D3&"'!"&CONFIG!L3&'SCORE CALC'!C3)&CHAR(10)&"Reputational Assessment: "&INDIRECT("'"&CONFIG!D3&"'!"&CONFIG!M3&'SCORE CALC'!C3)&CHAR(10)&"DPIA: "&INDIRECT("'"&CONFIG!D3&"'!"&CONFIG!N3&'SCORE CALC'!C3)&CHAR(10)&"DPSQ: "&INDIRECT("'"&CONFIG!D3&"'!"&CONFIG!O3&'SCORE CALC'!C3)&CHAR(10)&"VSDDT: "&INDIRECT("'"&CONFIG!D3&"'!"&CONFIG!P3&'SCORE CALC'!C3)&CHAR(10)&"Action Plan: "&INDIRECT("'"&CONFIG!D3&"'!"&CONFIG!Q3&'SCORE CALC'!C3) -> Financial Assessment: Yes Reputational Assessment: Yes DPIA: Not required – DPIA is not applicable for this service DPSQ: Not required – DPSQ is not applicable for this service VSDDT: Required – VSDDT completed and approved Action Plan: Yes – All action items have been completed and coordinated with relevant SME | K3: =IF(OR(F3="Below Expectation",F3="Unsatisfactory"),B3&" - "&C3,"")
A4: ='SCORE CALC'!A4 -> 3 | B4: =TRIM(LEFT(CONFIG!B4,FIND(" - ",CONFIG!B4)-1)) -> FPT Metrodata | C4: =TRIM(MID(CONFIG!B4,FIND(" - ",CONFIG!B4)+3,255)) -> Penetration Testing | D4: =CONFIG!C4 -> fauzi.aryanto@axa-mandiri.co.id | E4: ='SCORE CALC'!G4 -> 3 | F4: ='SCORE CALC'!H4 -> Meet Expectation | G4: =INDIRECT("'"&CONFIG!D4&"'!"&CONFIG!K4&'SCORE CALC'!C4) -> No need improvement | H4: ="Financial Assessment: "&INDIRECT("'"&CONFIG!D4&"'!"&CONFIG!L4&'SCORE CALC'!C4)&CHAR(10)&"Reputational Assessment: "&INDIRECT("'"&CONFIG!D4&"'!"&CONFIG!M4&'SCORE CALC'!C4)&CHAR(10)&"DPIA: "&INDIRECT("'"&CONFIG!D4&"'!"&CONFIG!N4&'SCORE CALC'!C4)&CHAR(10)&"DPSQ: "&INDIRECT("'"&CONFIG!D4&"'!"&CONFIG!O4&'SCORE CALC'!C4)&CHAR(10)&"VSDDT: "&INDIRECT("'"&CONFIG!D4&"'!"&CONFIG!P4&'SCORE CALC'!C4)&CHAR(10)&"Action Plan: "&INDIRECT("'"&CONFIG!D4&"'!"&CONFIG!Q4&'SCORE CALC'!C4) -> Financial Assessment: Yes Reputational Assessment: Yes DPIA: Not required – DPIA is not applicable for this service DPSQ: Not required – DPSQ is not applicable for this service VSDDT: Required – VSDDT completed and approved Action Plan: Yes – All action items have been completed and coordinated with relevant SME | K4: =IF(OR(F4="Below Expectation",F4="Unsatisfactory"),B4&" - "&C4,"")
A5: ='SCORE CALC'!A5 -> 4 | B5: =TRIM(LEFT(CONFIG!B5,FIND(" - ",CONFIG!B5)-1)) -> Satria Antaran Prima | C5: =TRIM(MID(CONFIG!B5,FIND(" - ",CONFIG!B5)+3,255)) -> Mailing Room | D5: =CONFIG!C5 -> ibnu.kumala@axa-mandiri.co.id | E5: ='SCORE CALC'!G5 -> 3.4041667 | F5: ='SCORE CALC'!H5 -> Meet Expectation | G5: =INDIRECT("'"&CONFIG!D5&"'!"&CONFIG!K5&'SCORE CALC'!C5) -> Over all mailing ok, please improve coordinated with Headoffice team for reduce complain/misscomm (ex case overseas shipment ) | H5: ="Financial Assessment: "&INDIRECT("'"&CONFIG!D5&"'!"&CONFIG!L5&'SCORE CALC'!C5)&CHAR(10)&"Reputational Assessment: "&INDIRECT("'"&CONFIG!D5&"'!"&CONFIG!M5&'SCORE CALC'!C5)&CHAR(10)&"DPIA: "&INDIRECT("'"&CONFIG!D5&"'!"&CONFIG!N5&'SCORE CALC'!C5)&CHAR(10)&"DPSQ: "&INDIRECT("'"&CONFIG!D5&"'!"&CONFIG!O5&'SCORE CALC'!C5)&CHAR(10)&"VSDDT: "&INDIRECT("'"&CONFIG!D5&"'!"&CONFIG!P5&'SCORE CALC'!C5)&CHAR(10)&"Action Plan: "&INDIRECT("'"&CONFIG!D5&"'!"&CONFIG!Q5&'SCORE CALC'!C5) -> Financial Assessment: Yes Reputational Assessment: Yes DPIA: Required – DPIA completed and approved DPSQ: Not required – DPSQ is not applicable for this service VSDDT: Required – VSDDT completed and approved Action Plan: Yes – All action items have been completed and coordinated with relevant SME | K5: =IF(OR(F5="Below Expectation",F5="Unsatisfactory"),B5&" - "&C5,"")
A6: ='SCORE CALC'!A6 -> 5 | B6: =TRIM(LEFT(CONFIG!B6,FIND(" - ",CONFIG!B6)-1)) -> Informasi Teknologi Indonesia | C6: =TRIM(MID(CONFIG!B6,FIND(" - ",CONFIG!B6)+3,255)) -> SMS Broadcast | D6: =CONFIG!C6 -> fifin.sarinurlita@axa-mandiri.co.id | E6: ='SCORE CALC'!G6 -> 3 | F6: ='SCORE CALC'!H6 -> Meet Expectation | G6: =INDIRECT("'"&CONFIG!D6&"'!"&CONFIG!K6&'SCORE CALC'!C6) -> Jatis has provided good service throughout this year | H6: ="Financial Assessment: "&INDIRECT("'"&CONFIG!D6&"'!"&CONFIG!L6&'SCORE CALC'!C6)&CHAR(10)&"Reputational Assessment: "&INDIRECT("'"&CONFIG!D6&"'!"&CONFIG!M6&'SCORE CALC'!C6)&CHAR(10)&"DPIA: "&INDIRECT("'"&CONFIG!D6&"'!"&CONFIG!N6&'SCORE CALC'!C6)&CHAR(10)&"DPSQ: "&INDIRECT("'"&CONFIG!D6&"'!"&CONFIG!O6&'SCORE CALC'!C6)&CHAR(10)&"VSDDT: "&INDIRECT("'"&CONFIG!D6&"'!"&CONFIG!P6&'SCORE CALC'!C6)&CHAR(10)&"Action Plan: "&INDIRECT("'"&CONFIG!D6&"'!"&CONFIG!Q6&'SCORE CALC'!C6) -> Financial Assessment: Yes Reputational Assessment: Yes DPIA: Required – DPIA completed and approved DPSQ: Required – DPSQ completed and approved VSDDT: Required – VSDDT completed and approved Action Plan: No – No action items were required | K6: =IF(OR(F6="Below Expectation",F6="Unsatisfactory"),B6&" - "&C6,"")
A7: ='SCORE CALC'!A7 -> 6 | B7: =TRIM(LEFT(CONFIG!B7,FIND(" - ",CONFIG!B7)-1)) -> Satria Antaran Prima | C7: =TRIM(MID(CONFIG!B7,FIND(" - ",CONFIG!B7)+3,255)) -> Courier Service | D7: =CONFIG!C7 -> fifin.sarinurlita@axa-mandiri.co.id | E7: ='SCORE CALC'!G7 -> 3 | F7: ='SCORE CALC'!H7 -> Meet Expectation | G7: =INDIRECT("'"&CONFIG!D7&"'!"&CONFIG!K7&'SCORE CALC'!C7) -> SAP has provided excellent service throughout this year | H7: ="Financial Assessment: "&INDIRECT("'"&CONFIG!D7&"'!"&CONFIG!L7&'SCORE CALC'!C7)&CHAR(10)&"Reputational Assessment: "&INDIRECT("'"&CONFIG!D7&"'!"&CONFIG!M7&'SCORE CALC'!C7)&CHAR(10)&"DPIA: "&INDIRECT("'"&CONFIG!D7&"'!"&CONFIG!N7&'SCORE CALC'!C7)&CHAR(10)&"DPSQ: "&INDIRECT("'"&CONFIG!D7&"'!"&CONFIG!O7&'SCORE CALC'!C7)&CHAR(10)&"VSDDT: "&INDIRECT("'"&CONFIG!D7&"'!"&CONFIG!P7&'SCORE CALC'!C7)&CHAR(10)&"Action Plan: "&INDIRECT("'"&CONFIG!D7&"'!"&CONFIG!Q7&'SCORE CALC'!C7) -> Financial Assessment: Yes Reputational Assessment: Yes DPIA: Required – DPIA completed and approved DPSQ: Required – DPSQ completed and approved VSDDT: Required – VSDDT completed and approved Action Plan: Yes – Action items identified, but follow‑up and coordination with relevant SME is still required | K7: =IF(OR(F7="Below Expectation",F7="Unsatisfactory"),B7&" - "&C7,"")
A8: ='SCORE CALC'!A8 -> 7 | B8: =TRIM(LEFT(CONFIG!B8,FIND(" - ",CONFIG!B8)-1)) -> Multifiling Mitra Indonesia | C8: =TRIM(MID(CONFIG!B8,FIND(" - ",CONFIG!B8)+3,255)) -> Record Management Service | D8: =CONFIG!C8 -> ibnu.kumala@axa-mandiri.co.id | E8: ='SCORE CALC'!G8 -> 3.0318182 | F8: ='SCORE CALC'!H8 -> Meet Expectation | G8: =INDIRECT("'"&CONFIG!D8&"'!"&CONFIG!K8&'SCORE CALC'!C8) -> impprove innovation dan simplyfy process | H8: ="Financial Assessment: "&INDIRECT("'"&CONFIG!D8&"'!"&CONFIG!L8&'SCORE CALC'!C8)&CHAR(10)&"Reputational Assessment: "&INDIRECT("'"&CONFIG!D8&"'!"&CONFIG!M8&'SCORE CALC'!C8)&CHAR(10)&"DPIA: "&INDIRECT("'"&CONFIG!D8&"'!"&CONFIG!N8&'SCORE CALC'!C8)&CHAR(10)&"DPSQ: "&INDIRECT("'"&CONFIG!D8&"'!"&CONFIG!O8&'SCORE CALC'!C8)&CHAR(10)&"VSDDT: "&INDIRECT("'"&CONFIG!D8&"'!"&CONFIG!P8&'SCORE CALC'!C8)&CHAR(10)&"Action Plan: "&INDIRECT("'"&CONFIG!D8&"'!"&CONFIG!Q8&'SCORE CALC'!C8) -> Financial Assessment: Yes Reputational Assessment: Yes DPIA: Required – DPIA completed and approved DPSQ: Required – DPSQ completed and approved VSDDT: Required – VSDDT completed and approved Action Plan: Yes – All action items have been completed and coordinated with relevant SME | K8: =IF(OR(F8="Below Expectation",F8="Unsatisfactory"),B8&" - "&C8,"")
A9: ='SCORE CALC'!A9 -> 8 | B9: =TRIM(LEFT(CONFIG!B9,FIND(" - ",CONFIG!B9)-1)) -> Indosat | C9: =TRIM(MID(CONFIG!B9,FIND(" - ",CONFIG!B9)+3,255)) -> Layanan PBX berbasiskan cloud dengan Teknologi SIP Trunk | D9: =CONFIG!C9 -> nuril.hudha@axa-mandiri.co.id | E9: ='SCORE CALC'!G9 -> 3.3184211 | F9: ='SCORE CALC'!H9 -> Meet Expectation | G9: =INDIRECT("'"&CONFIG!D9&"'!"&CONFIG!K9&'SCORE CALC'!C9) -> The performance is getting better, please keep improve the performance. | H9: ="Financial Assessment: "&INDIRECT("'"&CONFIG!D9&"'!"&CONFIG!L9&'SCORE CALC'!C9)&CHAR(10)&"Reputational Assessment: "&INDIRECT("'"&CONFIG!D9&"'!"&CONFIG!M9&'SCORE CALC'!C9)&CHAR(10)&"DPIA: "&INDIRECT("'"&CONFIG!D9&"'!"&CONFIG!N9&'SCORE CALC'!C9)&CHAR(10)&"DPSQ: "&INDIRECT("'"&CONFIG!D9&"'!"&CONFIG!O9&'SCORE CALC'!C9)&CHAR(10)&"VSDDT: "&INDIRECT("'"&CONFIG!D9&"'!"&CONFIG!P9&'SCORE CALC'!C9)&CHAR(10)&"Action Plan: "&INDIRECT("'"&CONFIG!D9&"'!"&CONFIG!Q9&'SCORE CALC'!C9) -> Financial Assessment: No Reputational Assessment: Yes DPIA: Required – DPIA completed and approved DPSQ: Not required – DPSQ is not applicable for this service VSDDT: Required – VSDDT completed and approved Action Plan: Yes – Action items identified, but follow‑up and coordination with relevant SME is still required | K9: =IF(OR(F9="Below Expectation",F9="Unsatisfactory"),B9&" - "&C9,"")
A10: ='SCORE CALC'!A10 -> 9 | B10: =TRIM(LEFT(CONFIG!B10,FIND(" - ",CONFIG!B10)-1)) -> Ciptadra Softindo | C10: =TRIM(MID(CONFIG!B10,FIND(" - ",CONFIG!B10)+3,255)) -> Pemeliharaan Axits & DMTM | D10: =CONFIG!C10 -> raninta.mahardi@axa-mandiri.co.id | E10: ='SCORE CALC'!G10 -> 4 | F10: ='SCORE CALC'!H10 -> Exceed Expectation | G10: =INDIRECT("'"&CONFIG!D10&"'!"&CONFIG!K10&'SCORE CALC'!C10) -> Performance is Good | H10: ="Financial Assessment: "&INDIRECT("'"&CONFIG!D10&"'!"&CONFIG!L10&'SCORE CALC'!C10)&CHAR(10)&"Reputational Assessment: "&INDIRECT("'"&CONFIG!D10&"'!"&CONFIG!M10&'SCORE CALC'!C10)&CHAR(10)&"DPIA: "&INDIRECT("'"&CONFIG!D10&"'!"&CONFIG!N10&'SCORE CALC'!C10)&CHAR(10)&"DPSQ: "&INDIRECT("'"&CONFIG!D10&"'!"&CONFIG!O10&'SCORE CALC'!C10)&CHAR(10)&"VSDDT: "&INDIRECT("'"&CONFIG!D10&"'!"&CONFIG!P10&'SCORE CALC'!C10)&CHAR(10)&"Action Plan: "&INDIRECT("'"&CONFIG!D10&"'!"&CONFIG!Q10&'SCORE CALC'!C10) -> Financial Assessment: Yes Reputational Assessment: Yes DPIA: Required – DPIA completed and approved DPSQ: Required – DPSQ completed and approved VSDDT: Required – VSDDT completed and approved Action Plan: Yes – All action items have been completed and coordinated with relevant SME | K10: =IF(OR(F10="Below Expectation",F10="Unsatisfactory"),B10&" - "&C10,"")
A11: ='SCORE CALC'!A11 -> 10 | B11: =TRIM(LEFT(CONFIG!B11,FIND(" - ",CONFIG!B11)-1)) -> Target Sukses Sinergi | C11: =TRIM(MID(CONFIG!B11,FIND(" - ",CONFIG!B11)+3,255)) -> Email Marketing Automation | D11: =CONFIG!C11 -> bella.depari@axa-mandiri.co.id | E11: ='SCORE CALC'!G11 -> 3.9 | F11: ='SCORE CALC'!H11 -> Meet Expectation | G11: =INDIRECT("'"&CONFIG!D11&"'!"&CONFIG!K11&'SCORE CALC'!C11) -> Harganya buat next contrac please murahin ya | H11: ="Financial Assessment: "&INDIRECT("'"&CONFIG!D11&"'!"&CONFIG!L11&'SCORE CALC'!C11)&CHAR(10)&"Reputational Assessment: "&INDIRECT("'"&CONFIG!D11&"'!"&CONFIG!M11&'SCORE CALC'!C11)&CHAR(10)&"DPIA: "&INDIRECT("'"&CONFIG!D11&"'!"&CONFIG!N11&'SCORE CALC'!C11)&CHAR(10)&"DPSQ: "&INDIRECT("'"&CONFIG!D11&"'!"&CONFIG!O11&'SCORE CALC'!C11)&CHAR(10)&"VSDDT: "&INDIRECT("'"&CONFIG!D11&"'!"&CONFIG!P11&'SCORE CALC'!C11)&CHAR(10)&"Action Plan: "&INDIRECT("'"&CONFIG!D11&"'!"&CONFIG!Q11&'SCORE CALC'!C11) -> Financial Assessment: Yes Reputational Assessment: Yes DPIA: Required – DPIA completed and approved DPSQ: Required – DPSQ completed and approved VSDDT: Required – VSDDT completed and approved Action Plan: Yes – All action items have been completed and coordinated with relevant SME | K11: =IF(OR(F11="Below Expectation",F11="Unsatisfactory"),B11&" - "&C11,"")
A12: ='SCORE CALC'!A12 -> 11 | B12: =TRIM(LEFT(CONFIG!B12,FIND(" - ",CONFIG!B12)-1)) -> Inmotion Inovasi Teknologi | C12: =TRIM(MID(CONFIG!B12,FIND(" - ",CONFIG!B12)+3,255)) -> Jasa Aplikasi Chatbot dan Live Chat | D12: =CONFIG!C12 -> djoko.djoko@axa-mandiri.co.id | E12: ='SCORE CALC'!G12 -> 4 | F12: ='SCORE CALC'!H12 -> Exceed Expectation | G12: =INDIRECT("'"&CONFIG!D12&"'!"&CONFIG!K12&'SCORE CALC'!C12) -> continue performing thorough and frequent periodic checks to ensure that during service hours, there are no issues that could disrupt operations and resolve the remaining unresolved 401 issue Berikan umpan balik Anda tentang BizChat | H12: ="Financial Assessment: "&INDIRECT("'"&CONFIG!D12&"'!"&CONFIG!L12&'SCORE CALC'!C12)&CHAR(10)&"Reputational Assessment: "&INDIRECT("'"&CONFIG!D12&"'!"&CONFIG!M12&'SCORE CALC'!C12)&CHAR(10)&"DPIA: "&INDIRECT("'"&CONFIG!D12&"'!"&CONFIG!N12&'SCORE CALC'!C12)&CHAR(10)&"DPSQ: "&INDIRECT("'"&CONFIG!D12&"'!"&CONFIG!O12&'SCORE CALC'!C12)&CHAR(10)&"VSDDT: "&INDIRECT("'"&CONFIG!D12&"'!"&CONFIG!P12&'SCORE CALC'!C12)&CHAR(10)&"Action Plan: "&INDIRECT("'"&CONFIG!D12&"'!"&CONFIG!Q12&'SCORE CALC'!C12) -> Financial Assessment: Yes Reputational Assessment: Yes DPIA: Required – DPIA completed and approved DPSQ: Required – DPSQ not yet completed or approved VSDDT: Required – VSDDT completed and approved Action Plan: Yes – All action items have been completed and coordinated with relevant SME | K12: =IF(OR(F12="Below Expectation",F12="Unsatisfactory"),B12&" - "&C12,"")
A13: ='SCORE CALC'!A13 -> 12 | B13: =TRIM(LEFT(CONFIG!B13,FIND(" - ",CONFIG!B13)-1)) -> Mitra Integrasi Informatika | C13: =TRIM(MID(CONFIG!B13,FIND(" - ",CONFIG!B13)+3,255)) -> SFDC Maintenance | D13: =CONFIG!C13 -> chandra.putra@axa-mandiri.co.id | E13: ='SCORE CALC'!G13 -> 4.8294872 | F13: ='SCORE CALC'!H13 -> Exceed Expectation | G13: =INDIRECT("'"&CONFIG!D13&"'!"&CONFIG!K13&'SCORE CALC'!C13) -> verall, the level of support has been satisfactory. The improvements carried out were highly effective, and several demands were consistent with the initial assessment and expectations. | H13: ="Financial Assessment: "&INDIRECT("'"&CONFIG!D13&"'!"&CONFIG!L13&'SCORE CALC'!C13)&CHAR(10)&"Reputational Assessment: "&INDIRECT("'"&CONFIG!D13&"'!"&CONFIG!M13&'SCORE CALC'!C13)&CHAR(10)&"DPIA: "&INDIRECT("'"&CONFIG!D13&"'!"&CONFIG!N13&'SCORE CALC'!C13)&CHAR(10)&"DPSQ: "&INDIRECT("'"&CONFIG!D13&"'!"&CONFIG!O13&'SCORE CALC'!C13)&CHAR(10)&"VSDDT: "&INDIRECT("'"&CONFIG!D13&"'!"&CONFIG!P13&'SCORE CALC'!C13)&CHAR(10)&"Action Plan: "&INDIRECT("'"&CONFIG!D13&"'!"&CONFIG!Q13&'SCORE CALC'!C13) -> Financial Assessment: No Reputational Assessment: No DPIA: Not required – DPIA is not applicable for this service DPSQ: Not required – DPSQ is not applicable for this service VSDDT: Required – VSDDT not yet completed or approved Action Plan: No – No action items were required | K13: =IF(OR(F13="Below Expectation",F13="Unsatisfactory"),B13&" - "&C13,"")
... A19: ='SCORE CALC'!A19 -> 18 | B19: =TRIM(LEFT(CONFIG!B19,FIND(" - ",CONFIG!B19)-1)) -> Karya Putra Surya Gemilang | C19: =TRIM(MID(CONFIG!B19,FIND(" - ",CONFIG!B19)+3,255)) -> Telemarketing Revamp Project | D19: =CONFIG!C19 -> reza.resdilana@axa-mandiri.co.id | E19: ='SCORE CALC'!G19 -> 3.0318182 | F19: ='SCORE CALC'!H19 -> Meet Expectation | G19: =INDIRECT("'"&CONFIG!D19&"'!"&CONFIG!K19&'SCORE CALC'!C19) -> Diharapkan untuk tim project yang diassign apabila CR sudah di signoff agar availibility dari resource ready | H19: ="Financial Assessment: "&INDIRECT("'"&CONFIG!D19&"'!"&CONFIG!L19&'SCORE CALC'!C19)&CHAR(10)&"Reputational Assessment: "&INDIRECT("'"&CONFIG!D19&"'!"&CONFIG!M19&'SCORE CALC'!C19)&CHAR(10)&"DPIA: "&INDIRECT("'"&CONFIG!D19&"'!"&CONFIG!N19&'SCORE CALC'!C19)&CHAR(10)&"DPSQ: "&INDIRECT("'"&CONFIG!D19&"'!"&CONFIG!O19&'SCORE CALC'!C19)&CHAR(10)&"VSDDT: "&INDIRECT("'"&CONFIG!D19&"'!"&CONFIG!P19&'SCORE CALC'!C19)&CHAR(10)&"Action Plan: "&INDIRECT("'"&CONFIG!D19&"'!"&CONFIG!Q19&'SCORE CALC'!C19) -> Financial Assessment: Yes Reputational Assessment: Yes DPIA: Required – DPIA completed and approved DPSQ: Required – DPSQ not yet completed or approved VSDDT: Required – VSDDT completed and approved Action Plan: Yes – All action items have been completed and coordinated with relevant SME | K19: =IF(OR(F19="Below Expectation",F19="Unsatisfactory"),B19&" - "&C19,"")

Sheet SUMMARY
A1: CRITICAL SUPPLIER PERFORMANCE REVIEW - SUMMARY
A2: Periode Review | B2: Q1 2026
A3: Jumlah Vendor Dievaluasi (dari RESULT) | B3: =COUNTA(RESULT!B2:B19) -> 18
A4: Total Vendor Kritis (Master List) - Input Manual | B4: 19
A5: % Vendor Dievaluasi | B5: =B3/B4 -> 0.94736842
A6: Jumlah "Meet / Exceed Expectation" | B6: =SUMPRODUCT(--(RESULT!F2:F19<>"Below Expectation"))-SUMPRODUCT(--(RESULT!F2:F19="Unsatisfactory")) -> 17
A7: Jumlah "Under Performance" (Below Expectation) | B7: =COUNTIF(RESULT!F2:F19,"Below Expectation")+COUNTIF(RESULT!F2:F19,"Unsatisfactory") -> 1
A8: Vendor Critical Below Expectation | B8: =_xlfn.TEXTJOIN(", ",TRUE(),RESULT!K2:K19) -> Arah Sejahtera Abadi - Perjanjian Sewa Menyewa

Sheet HISTORICAL
A1: Suppliers Name | B1: Service Scope | C1: 2024 | K1: 2025 | Y1: 2026
C2: Q1 | E2: Q2 | G2: Q3 | I2: Q4 | K2: Q1 | N2: Q2 | Q2: Q3 | T2: Repetition of Below Expectation | U2: Remarks | V2: Q4 | Y2: Q1
K3: Score | L3: User Comment | M3: Remarks | N3: Score | O3: User Comment | P3: Remarks | Q3: Score | R3: User Comment | S3: Remarks | V3: Score | W3: User Comment | X3: Remarks | Y3: Score | Z3: User Comment | AA3: Remarks
A4: INDOSAT | B4: LAYANAN PBX BERBASISKAN CLOUD DENGAN TEKNOLOGI SIP TRUNK | C4: 3 | D4: =IF(C4>4.99,"Exceptional",IF(C4>3.99,"Exceed Expectation",IF(C4>=2.99,"Meet Expectation",IF(C4>1.9,"Below Expectation","Unsatisfactory")))) -> Meet Expectation | E4: 3 | F4: =IF(E4>4.99,"Exceptional",IF(E4>3.99,"Exceed Expectation",IF(E4>=2.99,"Meet Expectation",IF(E4>1.9,"Below Expectation","Unsatisfactory")))) -> Meet Expectation | G4: 2.95 | H4: =IF(G4>4.99,"Exceptional",IF(G4>3.99,"Exceed Expectation",IF(G4>=2.99,"Meet Expectation",IF(G4>1.9,"Below Expectation","Unsatisfactory")))) -> Below Expectation | I4: 3 | J4: =IF(I4>4.99,"Exceptional",IF(I4>3.9,"Exceed Expectation",IF(I4>=2.99,"Meet Expectation",IF(I4>1.9,"Below Expectation","Unsatisfactory")))) -> Meet Expectation | K4: 2.345 | L4: Need improvement for the part of fair and to be more responsive to solve issues. | M4: =IF(K4>4.99,"Exceptional",IF(K4>3.9,"Exceed Expectation",IF(K4>=2.99,"Meet Expectation",IF(K4>1.9,"Below Expectation","Unsatisfactory")))) -> Below Expectation | N4: 1.99 | O4: 1. Dashboard access to required user 2. Response time to be improved as promised 3. To be more proactive in update the progress 4. To provide regular report (usage, recording, etc) | P4: =IF(N4>4.99,"Exceptional",IF(N4>3.9,"Exceed Expectation",IF(N4>=2.99,"Meet Expectation",IF(N4>1.9,"Below Expectation","Unsatisfactory")))) -> Below Expectation | Q4: 2.72 | R4: improve responsiveness when there is problem appear, and more proactive ask client follow up for the re-solution work or not after fixing. have plan maintenance and communicated earlier to client so client can aware about maintenance process. | S4: Below Expectation | T4: 3X | U4: Sudah dilakukan pemanggilan terhadap vendor yang bersangkutan dan pada Q3 terjadi perbaikan performance pada aspek kualitas jasa yang diberikan, dan pemenuhan timeline SLA | V4: 2.9825 | W4: PLEASE KINDLY IMPROVE REQUIRED REPORT DELIVERY AS AGREED WITH ANALYZED DATA FOR BUSINESS CONSIDERATION. | X4: BELOW EXPECTATION | Y4: =RESULT!E9 -> 3.3184211 | Z4: =RESULT!G9 -> The performance is getting better, please keep improve the performance. | AA4: =IF(Y4>4.99,"Exceptional",IF(Y4>3.99,"Exceed Expectation",IF(Y4>=2.99,"Meet Expectation",IF(Y4>1.9,"Below Expectation","Unsatisfactory")))) -> Meet Expectation
A5: INFORMASI TEKNOLOGI INDONESIA | B5: PENYEDIAAN JASA SMS BROADCAST DAN JASA SMS PULL; CONNECTIVITY PRIMARY LINK | C5: 3.78 | D5: =IF(C5>4.99,"Exceptional",IF(C5>3.99,"Exceed Expectation",IF(C5>=2.99,"Meet Expectation",IF(C5>1.9,"Below Expectation","Unsatisfactory")))) -> Meet Expectation | E5: 4.21 | F5: =IF(E5>4.99,"Exceptional",IF(E5>3.99,"Exceed Expectation",IF(E5>=2.99,"Meet Expectation",IF(E5>1.9,"Below Expectation","Unsatisfactory")))) -> Exceed Expectation | G5: 3 | H5: =IF(G5>4.99,"Exceptional",IF(G5>3.99,"Exceed Expectation",IF(G5>=2.99,"Meet Expectation",IF(G5>1.9,"Below Expectation","Unsatisfactory")))) -> Meet Expectation | I5: 3 | J5: =IF(I5>4.99,"Exceptional",IF(I5>3.9,"Exceed Expectation",IF(I5>=2.99,"Meet Expectation",IF(I5>1.9,"Below Expectation","Unsatisfactory")))) -> Meet Expectation | K5: 3 | L5: Sejauh ini untuk Vendor jaris tidak ada kendala, responsif. | M5: =IF(K5>4.99,"Exceptional",IF(K5>3.9,"Exceed Expectation",IF(K5>=2.99,"Meet Expectation",IF(K5>1.9,"Below Expectation","Unsatisfactory")))) -> Meet Expectation | N5: 3 | O5: So far Jatis has provided good service | P5: =IF(N5>4.99,"Exceptional",IF(N5>3.9,"Exceed Expectation",IF(N5>=2.99,"Meet Expectation",IF(N5>1.9,"Below Expectation","Unsatisfactory")))) -> Meet Expectation | Q5: 3 | R5: Secara keseluran service yang diberikan oleh JATIS baik | S5: Meet Expectation | T5: 0x | U5: - | V5: 3.0818182 | W5: STILL MEET REQUIREMENT | X5: MEET EXPECTATION | Y5: =RESULT!E6 -> 3 | Z5: =RESULT!G6 -> Jatis has provided good service throughout this year | AA5: =IF(Y5>4.99,"Exceptional",IF(Y5>3.99,"Exceed Expectation",IF(Y5>=2.99,"Meet Expectation",IF(Y5>1.9,"Below Expectation","Unsatisfactory")))) -> Meet Expectation
A6: MITRA INTEGRASI INFORMATIKA | B6: SFDC MAINTENANCE | C6: 3 | D6: =IF(C6>4.99,"Exceptional",IF(C6>3.99,"Exceed Expectation",IF(C6>=2.99,"Meet Expectation",IF(C6>1.9,"Below Expectation","Unsatisfactory")))) -> Meet Expectation | E6: 3 | F6: =IF(E6>4.99,"Exceptional",IF(E6>3.99,"Exceed Expectation",IF(E6>=2.99,"Meet Expectation",IF(E6>1.9,"Below Expectation","Unsatisfactory")))) -> Meet Expectation | G6: 3.96 | H6: =IF(G6>4.99,"Exceptional",IF(G6>3.99,"Exceed Expectation",IF(G6>=2.99,"Meet Expectation",IF(G6>1.9,"Below Expectation","Unsatisfactory")))) -> Meet Expectation | I6: 3.65 | J6: =IF(I6>4.99,"Exceptional",IF(I6>3.9,"Exceed Expectation",IF(I6>=2.99,"Meet Expectation",IF(I6>1.9,"Below Expectation","Unsatisfactory")))) -> Meet Expectation | K6: 3 | L6: 0 | M6: =IF(K6>4.99,"Exceptional",IF(K6>3.9,"Exceed Expectation",IF(K6>=2.99,"Meet Expectation",IF(K6>1.9,"Below Expectation","Unsatisfactory")))) -> Meet Expectation | N6: 4.4166667 | O6: The response from the MII Team to all the issues and needs we encountered has been quite good. They were able to promptly provide workarounds and broad solutions. The PIC assigned to the project was very communicative and responsible. Please maintain this level of performance, as we truly rely on it. | P6: =IF(N6>4.99,"Exceptional",IF(N6>3.9,"Exceed Expectation",IF(N6>=2.99,"Meet Expectation",IF(N6>1.9,"Below Expectation","Unsatisfactory")))) -> Exceed Expectation | Q6: 4.3538462 | R6: Good for MII, keep it up. | S6: Exceed Expectation | T6: 0x | U6: - | V6: 4.2730769 | W6: OVERALL, THE SUPPORT FROM MII IS VERY GOOD AND VERY HELPFUL, BOTH IN TERMS OF COMMUNICATION AND TECHNICAL ASPECTS, IT IS VERY EASY TO UNDERSTAND. | X6: EXCEED EXPECTATION | Y6: =RESULT!E13 -> 4.8294872 | Z6: =RESULT!G13 -> verall, the level of support has been satisfactory. The improvements carried out were highly effective, and several demands were consistent with the initial assessment and expectations. | AA6: =IF(Y6>4.99,"Exceptional",IF(Y6>3.99,"Exceed Expectation",IF(Y6>=2.99,"Meet Expectation",IF(Y6>1.9,"Below Expectation","Unsatisfactory")))) -> Exceed Expectation
A7: MULTIFILING MITRA INDONESIA | B7: RECORD MANAGEMENT SERVICE | C7: 3 | D7: =IF(C7>4.99,"Exceptional",IF(C7>3.99,"Exceed Expectation",IF(C7>=2.99,"Meet Expectation",IF(C7>1.9,"Below Expectation","Unsatisfactory")))) -> Meet Expectation | E7: 4 | F7: =IF(E7>4.99,"Exceptional",IF(E7>3.99,"Exceed Expectation",IF(E7>=2.99,"Meet Expectation",IF(E7>1.9,"Below Expectation","Unsatisfactory")))) -> Exceed Expectation | G7: 4 | H7: =IF(G7>4.99,"Exceptional",IF(G7>3.99,"Exceed Expectation",IF(G7>=2.99,"Meet Expectation",IF(G7>1.9,"Below Expectation","Unsatisfactory")))) -> Exceed Expectation | I7: 3.65 | J7: =IF(I7>4.99,"Exceptional",IF(I7>3.9,"Exceed Expectation",IF(I7>=2.99,"Meet Expectation",IF(I7>1.9,"Below Expectation","Unsatisfactory")))) -> Meet Expectation | K7: 3 | L7: - | M7: =IF(K7>4.99,"Exceptional",IF(K7>3.9,"Exceed Expectation",IF(K7>=2.99,"Meet Expectation",IF(K7>1.9,"Below Expectation","Unsatisfactory")))) -> Meet Expectation | N7: 3 | O7: overall OK | P7: =IF(N7>4.99,"Exceptional",IF(N7>3.9,"Exceed Expectation",IF(N7>=2.99,"Meet Expectation",IF(N7>1.9,"Below Expectation","Unsatisfactory")))) -> Meet Expectation | Q7: 3.9125 | R7: Untuk project destroy harga jangan mahal mahal | S7: Exceed Expectation | T7: 0x | U7: - | V7: 3.0693182 | W7: INOVASI FROM MMI FOR SIMPLIFY PROCESS STORAGE | X7: MEET EXPECTATION | Y7: =RESULT!E8 -> 3.0318182 | Z7: =RESULT!G8 -> impprove innovation dan simplyfy process | AA7: =IF(Y7>4.99,"Exceptional",IF(Y7>3.99,"Exceed Expectation",IF(Y7>=2.99,"Meet Expectation",IF(Y7>1.9,"Below Expectation","Unsatisfactory")))) -> Meet Expectation
A8: CIPTADRA SOFTINDO | B8: PEMELIHARAAN PERANGKAT LUNAK AXITS DAN PERANGKAT LUNAK DMTM | C8: 4.9 | D8: =IF(C8>4.99,"Exceptional",IF(C8>3.99,"Exceed Expectation",IF(C8>=2.99,"Meet Expectation",IF(C8>1.9,"Below Expectation","Unsatisfactory")))) -> Exceed Expectation | E8: 4.73 | F8: =IF(E8>4.99,"Exceptional",IF(E8>3.99,"Exceed Expectation",IF(E8>=2.99,"Meet Expectation",IF(E8>1.9,"Below Expectation","Unsatisfactory")))) -> Exceed Expectation | G8: 3.38 | H8: =IF(G8>4.99,"Exceptional",IF(G8>3.99,"Exceed Expectation",IF(G8>=2.99,"Meet Expectation",IF(G8>1.9,"Below Expectation","Unsatisfactory")))) -> Meet Expectation | I8: 3 | J8: =IF(I8>4.99,"Exceptional",IF(I8>3.9,"Exceed Expectation",IF(I8>=2.99,"Meet Expectation",IF(I8>1.9,"Below Expectation","Unsatisfactory")))) -> Meet Expectation | K8: 3.975 | L8: Ciptadra saat ini sudah sangat membantu IT AMFS apabila ada Issue atau Problem yang terjadi di DMTM dengan cepat. | M8: =IF(K8>4.99,"Exceptional",IF(K8>3.9,"Exceed Expectation",IF(K8>=2.99,"Meet Expectation",IF(K8>1.9,"Below Expectation","Unsatisfactory")))) -> Exceed Expectation | N8: 3.675 | O8: Ciptadra sudah bekerja dengan baik apabila ada Issue terjadi, sangat fast Response. | P8: =IF(N8>4.99,"Exceptional",IF(N8>3.9,"Exceed Expectation",IF(N8>=2.99,"Meet Expectation",IF(N8>1.9,"Below Expectation","Unsatisfactory")))) -> Meet Expectation | Q8: 3.75 | R8: - | S8: Meet Expectation | T8: 0x | U8: - | V8: 4.2 | W8: - | X8: EXCEED EXPECTATION | Y8: =RESULT!E10 -> 4 | Z8: =RESULT!G10 -> Performance is Good | AA8: =IF(Y8>4.99,"Exceptional",IF(Y8>3.99,"Exceed Expectation",IF(Y8>=2.99,"Meet Expectation",IF(Y8>1.9,"Below Expectation","Unsatisfactory")))) -> Exceed Expectation
A9: INMOTION INOVASI TEKNOLOGI | B9: JASA APLIKASI CHATBOT DAN LIVE CHAT | C9: 3 | D9: =IF(C9>4.99,"Exceptional",IF(C9>3.99,"Exceed Expectation",IF(C9>=2.99,"Meet Expectation",IF(C9>1.9,"Below Expectation","Unsatisfactory")))) -> Meet Expectation | E9: 3 | F9: =IF(E9>4.99,"Exceptional",IF(E9>3.99,"Exceed Expectation",IF(E9>=2.99,"Meet Expectation",IF(E9>1.9,"Below Expectation","Unsatisfactory")))) -> Meet Expectation | G9: 3.09 | H9: =IF(G9>4.99,"Exceptional",IF(G9>3.99,"Exceed Expectation",IF(G9>=2.99,"Meet Expectation",IF(G9>1.9,"Below Expectation","Unsatisfactory")))) -> Meet Expectation | I9: 3 | J9: =IF(I9>4.99,"Exceptional",IF(I9>3.9,"Exceed Expectation",IF(I9>=2.99,"Meet Expectation",IF(I9>1.9,"Below Expectation","Unsatisfactory")))) -> Meet Expectation | K9: 2.121875 | L9: More responsive in solving problems and always providing information on the latest features to support future customer service. | M9: =IF(K9>4.99,"Exceptional",IF(K9>3.9,"Exceed Expectation",IF(K9>=2.99,"Meet Expectation",IF(K9>1.9,"Below Expectation","Unsatisfactory")))) -> Below Expectation | N9: 2.9890625 | O9: Maintain the consistency and communication that has been established. Always take the initiative to provide the latest information regarding developments in the Live Chat service. | P9: =IF(N9>4.99,"Exceptional",IF(N9>3.9,"Exceed Expectation",IF(N9>=2.99,"Meet Expectation",IF(N9>1.9,"Below Expectation","Unsatisfactory")))) -> Below Expectation | Q9: 3 | R9: Tetap selalu berikan Service yang Terbaik | S9: Meet Expectation | T9: 0x | U9: Sudah dilakukan pemanggilan terhadap vendor yang bersangkutan dan pada Q3 terjadi perbaikan performance | V9: 3.65 | W9: - | X9: MEET EXPECTATION | Y9: =RESULT!E12 -> 4 | Z9: =RESULT!G12 -> continue performing thorough and frequent periodic checks to ensure that during service hours, there are no issues that could disrupt operations and resolve the remaining unresolved 401 issue Berikan umpan balik Anda tentang BizChat | AA9: =IF(Y9>4.99,"Exceptional",IF(Y9>3.99,"Exceed Expectation",IF(Y9>=2.99,"Meet Expectation",IF(Y9>1.9,"Below Expectation","Unsatisfactory")))) -> Exceed Expectation
A10: SATRIA ANTARAN PRIMA TBK | B10: PENGIRIMAN POLIS DOKUMEN DAN PAKET DALAM NEGERI | C10: 3.75 | D10: =IF(C10>4.99,"Exceptional",IF(C10>3.99,"Exceed Expectation",IF(C10>=2.99,"Meet Expectation",IF(C10>1.9,"Below Expectation","Unsatisfactory")))) -> Meet Expectation | E10: 3.83 | F10: =IF(E10>4.99,"Exceptional",IF(E10>3.99,"Exceed Expectation",IF(E10>=2.99,"Meet Expectation",IF(E10>1.9,"Below Expectation","Unsatisfactory")))) -> Meet Expectation | G10: 2.74 | H10: =IF(G10>4.99,"Exceptional",IF(G10>3.99,"Exceed Expectation",IF(G10>=2.99,"Meet Expectation",IF(G10>1.9,"Below Expectation","Unsatisfactory")))) -> Below Expectation | I10: 2.725 | J10: =IF(I10>4.99,"Exceptional",IF(I10>3.9,"Exceed Expectation",IF(I10>=2.99,"Meet Expectation",IF(I10>1.9,"Below Expectation","Unsatisfactory")))) -> Below Expectation | K10: 2.86 | L10: User 1: ada progress positif dari SAP untuk memperbaiki apa yang kurang di periode sebelumnya. User 2: late respon terhadap keluhan pickup pengiriman dan validasi pengiriman dari PIC Unie. Draft invoice yang dikirimkan blm tertata dengan baik atau sesuai dengan kesamaan data dari User. | M10: =IF(K10>4.99,"Exceptional",IF(K10>3.9,"Exceed Expectation",IF(K10>=2.99,"Meet Expectation",IF(K10>1.9,"Below Expectation","Unsatisfactory")))) -> Below Expectation | N10: 2.6166667 | O10: - SAP should be improve the quality of its couriers regarding accuracy of delivery status. - komunikasi dgn Unie sangat sulit, slow respons, invoice yg dikirimkan juga tidak ada respon dan updatenya ketika sudah di reminder. pickup dokumen secara manual (tidak menggunakan sistem) masih berjalan dan diterima oleh SAP. | P10: =IF(N10>4.99,"Exceptional",IF(N10>3.9,"Exceed Expectation",IF(N10>=2.99,"Meet Expectation",IF(N10>1.9,"Below Expectation","Unsatisfactory")))) -> Below Expectation | Q10: 2.5 | R10: User 1: invoice periode maret-juni 2025 tdk ada update. update status informasi pengiriman tidak valid (fake shipment), kendala akun tidak dapat melakukan input, pickup manual masih terus berjalan (no commit). dah laah caapee User 2: sudah ada kemajuan mengenai respon terhadap complain handling oleh SAP | S10: Below Expectation | T10: 5X | U10: Pada periode Q2, Business User memberikan konfirmasi bahwa SAP diberi penilaian positif atas adanya perubahan dari proses pickup dokumen dan pengiriman invoice sebagai tanggapan kepada procurement ketika procurement memberikan masukan untuk melakukan penggantian vendor. Pada periode Q3, User kembali memberikan nilai below expectation dan akan dilakukan pemanggilan kepada vendor terkait. Paralel dengan proses tersebut, procurement melakukan arrangement untuk pemilihan vendor alternatif atas kebutuhan courier services. | V10: 2.9611111 | W10: VEMDOR SAP ADA PENINGKATAN TERUTAMA DI KOMUNIKASI PIC NYA | X10: BELOW EXPECTATION | Y10: =RESULT!E7 -> 3 | Z10: =RESULT!G7 -> SAP has provided excellent service throughout this year | AA10: =IF(Y10>4.99,"Exceptional",IF(Y10>3.99,"Exceed Expectation",IF(Y10>=2.99,"Meet Expectation",IF(Y10>1.9,"Below Expectation","Unsatisfactory")))) -> Meet Expectation
A11: SATRIA ANTARAN PRIMA TBK | B11: MAILING ROOM | C11: N/A | D11: N/A | E11: N/A | F11: N/A | G11: N/A | H11: N/A | I11: N/A | J11: N/A | K11: 3 | L11: - | M11: =IF(K11>4.99,"Exceptional",IF(K11>3.9,"Exceed Expectation",IF(K11>=2.99,"Meet Expectation",IF(K11>1.9,"Below Expectation","Unsatisfactory")))) -> Meet Expectation | N11: N/A | O11: N/A | P11: N/A | Q11: 3.9125 | R11: tingkatkan lebih performancenya | S11: Exceed Expectation | T11: 0x | U11: - | V11: 3.05 | W11: NEED INOVATION FROM SAP FOR SIMPLIFY PROCESS AT AXA MANDIRI MAILING ROOM | X11: MEET EXPECTATION | Y11: =RESULT!E5 -> 3.4041667 | Z11: =RESULT!G5 -> Over all mailing ok, please improve coordinated with Headoffice team for reduce complain/misscomm (ex case overseas shipment ) | AA11: =IF(Y11>4.99,"Exceptional",IF(Y11>3.99,"Exceed Expectation",IF(Y11>=2.99,"Meet Expectation",IF(Y11>1.9,"Below Expectation","Unsatisfactory")))) -> Meet Expectation
A12: TARGET SUKSES SINERGI | B12: PENGIRIMAN EMAIL MARKETING AUTOMATION | C12: 2.85 | D12: =IF(C12>4.99,"Exceptional",IF(C12>3.99,"Exceed Expectation",IF(C12>=2.99,"Meet Expectation",IF(C12>1.9,"Below Expectation","Unsatisfactory")))) -> Below Expectation | E12: 3.28 | F12: =IF(E12>4.99,"Exceptional",IF(E12>3.99,"Exceed Expectation",IF(E12>=2.99,"Meet Expectation",IF(E12>1.9,"Below Expectation","Unsatisfactory")))) -> Meet Expectation | G12: 4 | H12: =IF(G12>4.99,"Exceptional",IF(G12>3.99,"Exceed Expectation",IF(G12>=2.99,"Meet Expectation",IF(G12>1.9,"Below Expectation","Unsatisfactory")))) -> Exceed Expectation | I12: 3.3125 | J12: =IF(I12>4.99,"Exceptional",IF(I12>3.9,"Exceed Expectation",IF(I12>=2.99,"Meet Expectation",IF(I12>1.9,"Below Expectation","Unsatisfactory")))) -> Meet Expectation | K12: 3.7444444 | L12: Overall our partnership going well | M12: =IF(K12>4.99,"Exceptional",IF(K12>3.9,"Exceed Expectation",IF(K12>=2.99,"Meet Expectation",IF(K12>1.9,"Below Expectation","Unsatisfactory")))) -> Meet Expectation | N12: 4 | O12: Please keep up the good work! | P12: =IF(N12>4.99,"Exceptional",IF(N12>3.9,"Exceed Expectation",IF(N12>=2.99,"Meet Expectation",IF(N12>1.9,"Below Expectation","Unsatisfactory")))) -> Exceed Expectation | Q12: 3 | R12: Overall Good | S12: Meet Expectation | T12: 0x | U12: - | V12: 3.65 | W12: GOOD | X12: MEET EXPECTATION | Y12: =RESULT!E11 -> 3.9 | Z12: =RESULT!G11 -> Harganya buat next contrac please murahin ya | AA12: =IF(Y12>4.99,"Exceptional",IF(Y12>3.99,"Exceed Expectation",IF(Y12>=2.99,"Meet Expectation",IF(Y12>1.9,"Below Expectation","Unsatisfactory")))) -> Meet Expectation
A13: WIZ TECHNOLOGY INDONESIA | B13: VOICE BOT REMINDER CALL | C13: 3 | D13: =IF(C13>4.99,"Exceptional",IF(C13>3.99,"Exceed Expectation",IF(C13>=2.99,"Meet Expectation",IF(C13>1.9,"Below Expectation","Unsatisfactory")))) -> Meet Expectation | E13: 3.61 | F13: =IF(E13>4.99,"Exceptional",IF(E13>3.99,"Exceed Expectation",IF(E13>=2.99,"Meet Expectation",IF(E13>1.9,"Below Expectation","Unsatisfactory")))) -> Meet Expectation | G13: 3.4 | H13: =IF(G13>4.99,"Exceptional",IF(G13>3.99,"Exceed Expectation",IF(G13>=2.99,"Meet Expectation",IF(G13>1.9,"Below Expectation","Unsatisfactory")))) -> Meet Expectation | I13: 3.0875 | J13: =IF(I13>4.99,"Exceptional",IF(I13>3.9,"Exceed Expectation",IF(I13>=2.99,"Meet Expectation",IF(I13>1.9,"Below Expectation","Unsatisfactory")))) -> Meet Expectation | K13: 3.0388889 | L13: so far wiz.AI sudah memenuhi apa yang menjadi kebutuhan kami | M13: =IF(K13>4.99,"Exceptional",IF(K13>3.9,"Exceed Expectation",IF(K13>=2.99,"Meet Expectation",IF(K13>1.9,"Below Expectation","Unsatisfactory")))) -> Meet Expectation | N13: 3.5444444 | O13: needs better communication for quicker responses. | P13: =IF(N13>4.99,"Exceptional",IF(N13>3.9,"Exceed Expectation",IF(N13>=2.99,"Meet Expectation",IF(N13>1.9,"Below Expectation","Unsatisfactory")))) -> Meet Expectation | Q13: 3 | R13: sudah baik | S13: Meet Expectation | T13: 0x | U13: - | V13: 3.46875 | W13: WE EXPECT INITIATIVE TO BE TAKEN IN IMPLEMENTING MITIGATION MEASURES AND IN ACCELERATING THE PROCESS WITHIN COLLABORATION WITH WIZ AI. | X13: MEET EXPECTATION | Y13: 0 | Z13: 0
A14: KARYAPUTRA SURYAGEMILANG | B14: TELEMARKETING REVAMP PROJECT | C14: 3.46 | D14: =IF(C14>4.99,"Exceptional",IF(C14>3.99,"Exceed Expectation",IF(C14>=2.99,"Meet Expectation",IF(C14>1.9,"Below Expectation","Unsatisfactory")))) -> Meet Expectation | E14: 3.46 | F14: =IF(E14>4.99,"Exceptional",IF(E14>3.99,"Exceed Expectation",IF(E14>=2.99,"Meet Expectation",IF(E14>1.9,"Below Expectation","Unsatisfactory")))) -> Meet Expectation | G14: 3.86 | H14: =IF(G14>4.99,"Exceptional",IF(G14>3.99,"Exceed Expectation",IF(G14>=2.99,"Meet Expectation",IF(G14>1.9,"Below Expectation","Unsatisfactory")))) -> Meet Expectation | I14: 3 | J14: =IF(I14>4.99,"Exceptional",IF(I14>3.9,"Exceed Expectation",IF(I14>=2.99,"Meet Expectation",IF(I14>1.9,"Below Expectation","Unsatisfactory")))) -> Meet Expectation | K14: 3.1807692 | L14: Need to speed up the investigation and fixing process when issues arise. | M14: =IF(K14>4.99,"Exceptional",IF(K14>3.9,"Exceed Expectation",IF(K14>=2.99,"Meet Expectation",IF(K14>1.9,"Below Expectation","Unsatisfactory")))) -> Meet Expectation | N14: 2.9371795 | O14: As we have many projects involved KPSG in AMFS, please do maintain the dedicated team for TM Revamp. Currently activities in other projects may impact in TM Revamp project, i.e. PureCloud Decommissioned impact in TM Revamp activities (huddle meeting) and deliverables (CRs). We believe each project has different urgency and separate budget which need to be considered not impacted each other. | P14: =IF(N14>4.99,"Exceptional",IF(N14>3.9,"Exceed Expectation",IF(N14>=2.99,"Meet Expectation",IF(N14>1.9,"Below Expectation","Unsatisfactory")))) -> Below Expectation | Q14: 2.4272727 | R14: We concenrn about human resource, somehow we need extra effort time to make Change Request, Assesment Scope and issue. It takes long time to asses new Change Request because availibility human resources. | S14: Below Expectation | T14: 2x | U14: Pada periode Q2 mendapatkan hasil below expectation dan procurement sudah lakukan pemanggilan untuk menyampaikan evaluasi performance tersebut bersama sama dengan business user. Pada periode Q3, business user menyampaikan concern kembali dengan hasil below expectation, dan akan dilakukan pemanggilan kembali kepada KPSG. | V14: 3.5181818 | W14: PLEASE BE MORE PERFORMED BECAUSE OUR NEEDS IS SO FAST FOR STRATEGIC DELIVERY | X14: MEET EXPECTATION | Y14: =RESULT!E19 -> 3.0318182 | Z14: =RESULT!G19 -> Diharapkan untuk tim project yang diassign apabila CR sudah di signoff agar availibility dari resource ready | AA14: =IF(Y14>4.99,"Exceptional",IF(Y14>3.99,"Exceed Expectation",IF(Y14>=2.99,"Meet Expectation",IF(Y14>1.9,"Below Expectation","Unsatisfactory")))) -> Meet Expectation
A15: ARAH SEJAHTERA ABADI | B15: PERJANJIAN SEWA MENYEWA | C15: N/A | D15: N/A | E15: 3 | F15: =IF(E15>4.99,"Exceptional",IF(E15>3.99,"Exceed Expectation",IF(E15>=2.99,"Meet Expectation",IF(E15>1.9,"Below Expectation","Unsatisfactory")))) -> Meet Expectation | G15: 3 | H15: =IF(G15>4.99,"Exceptional",IF(G15>3.99,"Exceed Expectation",IF(G15>=2.99,"Meet Expectation",IF(G15>1.9,"Below Expectation","Unsatisfactory")))) -> Meet Expectation | I15: 3.35 | J15: =IF(I15>4.99,"Exceptional",IF(I15>3.9,"Exceed Expectation",IF(I15>=2.99,"Meet Expectation",IF(I15>1.9,"Below Expectation","Unsatisfactory")))) -> Meet Expectation | K15: 2.8409091 | L15: Improve Resolution repair, for this year resolution fro problem dusty and project smell CCC impact project from another tenant behind CCC GF ( NOV 2024 until now still not yet solution ) | M15: =IF(K15>4.99,"Exceptional",IF(K15>3.9,"Exceed Expectation",IF(K15>=2.99,"Meet Expectation",IF(K15>1.9,"Below Expectation","Unsatisfactory")))) -> Below Expectation | N15: 2.7727273 | O15: for improvment is Improve resolusi repair/corective device Building in tenant area | P15: =IF(N15>4.99,"Exceptional",IF(N15>3.9,"Exceed Expectation",IF(N15>=2.99,"Meet Expectation",IF(N15>1.9,"Below Expectation","Unsatisfactory")))) -> Below Expectation | Q15: 2 | R15: adanya SLA atau KPI utuk review kuncit | S15: Below Expectation | T15: 3x | U15: Pada periode Q1, Q2, dan Q3, hasil penilaian evaluasinya cenderung turun karena dari pihak Kuningan City tidak bersedia dianggap sebagai vendor / supplier, yang bisa diberlakukan penilaian performance atas layanan yang diberikan. Dari sisi operasional, memberikan nilai below expectation karena pihak Kuncit dirasa kurang responsif dalam menanggapi keluhan. | V15: 2.9611111 | W15: KUNCIT SUPPORT FOR SPACE AMFS (GIVE MORE ADVANTAGE FREE CHARGE FOR 12), FOR THE REPAIR /SOLUTION NEED MORE IMPROVE TIME OR QUALITY | X15: BELOW EXPECTATION | Y15: =RESULT!E16 -> 2.9611111 | Z15: =RESULT!G16 -> Improve quality service, specially for leakage, | AA15: =IF(Y15>4.99,"Exceptional",IF(Y15>3.99,"Exceed Expectation",IF(Y15>=2.99,"Meet Expectation",IF(Y15>1.9,"Below Expectation","Unsatisfactory")))) -> Below Expectation
A16: DELOITTE CONSULTING | B16: DATA PRIVACY TOOLS & PELATIHAN PERSONAL DATA PROTECTION (PDP) | C16: N/A | D16: N/A | E16: N/A | F16: N/A | G16: N/A | H16: N/A | I16: 3.2333333 | J16: =IF(I16>4.99,"Exceptional",IF(I16>3.9,"Exceed Expectation",IF(I16>=2.99,"Meet Expectation",IF(I16>1.9,"Below Expectation","Unsatisfactory")))) -> Meet Expectation | K16: 2.9708333 | L16: They need to deepen their product knowledge so that they can be right on target in providing solutions. | M16: =IF(K16>4.99,"Exceptional",IF(K16>3.9,"Exceed Expectation",IF(K16>=2.99,"Meet Expectation",IF(K16>1.9,"Below Expectation","Unsatisfactory")))) -> Below Expectation | N16: 2.8833333 | O16: Understand more about product feature knowledge so that vendors can explain accurately and convincingly when there is trouble or product limitations. | P16: =IF(N16>4.99,"Exceptional",IF(N16>3.9,"Exceed Expectation",IF(N16>=2.99,"Meet Expectation",IF(N16>1.9,"Below Expectation","Unsatisfactory")))) -> Below Expectation | Q16: 3.1 | R16: More coordination with PIC Principal Product (Securiti.ai) to get information regarding product updates earlier. | S16: Meet Expectation | T16: 0x | U16: - | V16: 3.1166667 | W16: MORE COORDINATION WITH PIC PRINCIPAL PRODUCT (SECURITI.AI) TO GET INFORMATION REGARDING PRODUCT UPDATES EARLIER. | X16: MEET EXPECTATION | Y16: =RESULT!E17 -> 3.1636364 | Z16: =RESULT!G17 -> Need more improvement regarding initiative to take mitigation/preventive action to prevent the problem from recurring/current issue. | AA16: =IF(Y16>4.99,"Exceptional",IF(Y16>3.99,"Exceed Expectation",IF(Y16>=2.99,"Meet Expectation",IF(Y16>1.9,"Below Expectation","Unsatisfactory")))) -> Meet Expectation
A17: SUTRA MANAGEMENT CONSULTANCIES | B17: IMPLEMENTASI SAS IFRS17 | C17: N/A | D17: N/A | E17: N/A | F17: N/A | G17: N/A | H17: N/A | I17: N/A | J17: N/A | K17: 3.1866667 | L17: Sometimes the vendor must think out-of-the box meaning that they need to be "somehow creative enough" in expediting the problem-solution approaches to any issues being raised by us as customers in the fields of both IT and Finance/Actuary. They seems to play "by the book" instead of proposing the new ideas and thoughts flexibel enough to be implemented as long as not crossing the compliance issues. Those kind ideas that can help us to have more effective and productive outcomes in the very challenging timeline. | M17: =IF(K17>4.99,"Exceptional",IF(K17>3.9,"Exceed Expectation",IF(K17>=2.99,"Meet Expectation",IF(K17>1.9,"Below Expectation","Unsatisfactory")))) -> Meet Expectation | N17: 3.6733333 | O17: In overall is above the "Good Criteria" except when starting to develop the infrastructure in the beginning because the development team of this vendor is not in Jakarta but instead in India that added extra challenges for us to communicate (in English) and coordinate (long distance) | P17: =IF(N17>4.99,"Exceptional",IF(N17>3.9,"Exceed Expectation",IF(N17>=2.99,"Meet Expectation",IF(N17>1.9,"Below Expectation","Unsatisfactory")))) -> Meet Expectation | Q17: 3.5166667 | R17: I think we need to be fair that the PSAK117 Methodology is the new thing that even for the vendor to execute in the CSM Engine needs to know some critical particular requirements that business users expect for CSM to deliver. Therefore, CSM Engine needs to be customized, and this takes time from the vendor to adjust/modify. My suggestion for the vendor is to always provide a stand-by expertise in the field of IFRS17 Methodoly, and he/she is able to explain clearly to users how these things work in the CSM System, and how users should provide required items in our existing data input system. Mutual understanding is the key; system modification is easy to implement; and expertise people from the vendor are always stand by | S17: Meet Expectation | T17: 0x | U17: - | V17: 3.8666667 | W17: N/A | X17: MEET EXPECTATION | Y17: =RESULT!E14 -> 3.6833333 | Z17: =RESULT!G14 -> Local vendor Sutra is affiliated with SAS Technology which is known as more expensive system compared to other vendors during the Vendor Bidding Process. However, SAS Technology System has been used in few well-known insurance companies in Indonesia, so it is easier to get the review and information; mostly positive. | AA17: =IF(Y17>4.99,"Exceptional",IF(Y17>3.99,"Exceed Expectation",IF(Y17>=2.99,"Meet Expectation",IF(Y17>1.9,"Below Expectation","Unsatisfactory")))) -> Meet Expectation
A18: TMF INDONESIA | B18: PAYROLL | K18: N/A | L18: N/A | M18: N/A | N18: N/A | O18: N/A | P18: N/A | Q18: N/A | R18: N/A | S18: N/A | T18: 3 | U18: BETTER COORDINATION THAN 2025, REPORTS ARE ALWAYS REVIEWED BY RELATED MANAGER BEFORE SUBMIT TO AMFS PIC. | Y18: =RESULT!E18 -> 3 | Z18: =RESULT!G18 -> Always check and recheck the task in internal PIC TMF before send the report to AMFS PIC | AA18: =IF(Y18>4.99,"Exceptional",IF(Y18>3.99,"Exceed Expectation",IF(Y18>=2.99,"Meet Expectation",IF(Y18>1.9,"Below Expectation","Unsatisfactory")))) -> Meet Expectation
A19: REYCOM DOCUMENT SOLUTION | B19: PRINTING & DMC | K19: N/A | L19: N/A | M19: N/A | N19: N/A | O19: N/A | P19: N/A | Q19: N/A | R19: N/A | S19: N/A | T19: 3.5416667 | U19: PLEASE BE MORE PERFORMED BECAUSE OUR NEEDS IS SO FAST FOR STRATEGIC DELIVERY | Y19: =RESULT!E15 -> 4.7666667 | Z19: =RESULT!G15 -> More inovation for 2026 | AA19: =IF(Y19>4.99,"Exceptional",IF(Y19>3.99,"Exceed Expectation",IF(Y19>=2.99,"Meet Expectation",IF(Y19>1.9,"Below Expectation","Unsatisfactory")))) -> Exceed Expectation
A20: FPT METRODATA INDONESIA | B20: PENETRATION TEST | Y20: =RESULT!E4 -> 3 | Z20: =RESULT!G4 -> No need improvement | AA20: =IF(Y20>4.99,"Exceptional",IF(Y20>3.99,"Exceed Expectation",IF(Y20>=2.99,"Meet Expectation",IF(Y20>1.9,"Below Expectation","Unsatisfactory")))) -> Meet Expectation
A21: IPROTEKSI TELEMATIKA | B21: PENETRATION TEST | Y21: =RESULT!E3 -> 4 | Z21: =RESULT!G3 -> no need improvement | AA21: =IF(Y21>4.99,"Exceptional",IF(Y21>3.99,"Exceed Expectation",IF(Y21>=2.99,"Meet Expectation",IF(Y21>1.9,"Below Expectation","Unsatisfactory")))) -> Exceed Expectation
A22: ITSEC ASIA | B22: PENETRATION TEST | Y22: =RESULT!E2 -> 3 | Z22: =RESULT!G2 -> Currently no need improvement | AA22: =IF(Y22>4.99,"Exceptional",IF(Y22>3.99,"Exceed Expectation",IF(Y22>=2.99,"Meet Expectation",IF(Y22>1.9,"Below Expectation","Unsatisfactory")))) -> Meet Expectation

Sheet RAW DATA Q1 - 1
A1: Start time | B1: Completion time | C1: Email | D1: Name | E1: User Name | F1: Supplier and Service | G1: How would you rate Supplier's ability to understand and meet your needs? | H1: How would you rate the Quality of fulfillment of specifications required by Perfect Assistant? | I1: How would you rate the data model of source of leads on customer level, which contains Existing Customers, Potential Customers, and Hot Leads? | J1: How would you rate the Leads activity evidence and result details, such as Call, Appointment, Visit, and Closing result evidence? | K1: How would you rate the Sales Activity Management process, as tracked by the Sales Leader and sorted by time range? | L1: How would you rate the Notification to Sales Team which consist of: | M1: How would you rate the telephony features which enable to mask either/both Customers’ and Agents’ personal phone number for better customer service and better protection of Customers’ privacy? | N1: How would you rate the assignment features which enable leaders to re-assign the leads to other FA (e.g. FA resigned or move to other branch then the Leads will be assigned to existing FA)? | O1: How would you rate the System Availability, Redundancy, and Overload Protection? | P1: How would you rate the Security Access? | Q1: How would you rate the Audit Trail? | R1: How would you rate the Overall Supplier's reports including Report of Leads activity record and tracking? | S1: How would you rate the Resources / Authorized Personel Commitment and Qualification? | T1: How would you rate supplier initiative to take mitigation/preventive action to prevent recurring problem? | U1: How would you rate supplier compliance with administrative processes, including completion of draft cooperation contract? | V1: How would you rate the Integration with Perfect Assistant? | W1: How would you rate the SIT dan UAT Phase? | X1: How would you rate the use of channels to avoid customer data leaks? | Y1: How would you rate the Access to the recording dashboard? | Z1: How would you rate the Security compare to its standard? | AA1: How would you rate Supplier's ability to understand and meet your needs?1 | AB1: How would you rate the goods/services provided by the Supplier against the agreed standards? | AC1: How would you rate the accuracy of the data in the Supplier's reports? | AD1: How would you rate overall quality of the work reports provided by the Supplier? | AE1: How would you rate the solutions provided when there is trouble? | AF1: How would you rate the resolution to the problem that occurred? | AG1: How would you rate the speed of resolution given to problems that occur? | AH1: How would you rate the supplier initiative to take mitigation/preventive action to prevent the problem from recurring? | AI1: How would you rate supplier compliance with administrative processes, including completion of draft cooperation contract?1 | AJ1: How would you rate the Implementation of UAT? | AK1: How would you rate the maintenance includes bug fixing and support for system problems that occur in the JATIS MOBILE application/service? | AL1: How would you rate Supplier's ability to understand and meet your needs?2 | AM1: How would you rate the The goods/services provided by the Supplier against the agreed standards? | AN1: How would you rate the General support and maintenance requirement? | AO1: How would you rate the Performance Management Requirement which includes to support low latency, documentation, performance monitoring, and any major or minor updates? | AP1: How would you rate the Security Management Requirement? | AQ1: How would you rate the Supporting Model which includes onsite support from dedicated engineers and its service level agreement (SLA)? | AR1: How would you rate the accuracy of the data in the Supplier's reports?1 | AS1: How would you rate overall quality of the work reports provided by the Supplier?1 | AT1: How would you rate the solutions provided when there is trouble?1 | AU1: How would you rate the resolution to the problem that occurred?1 | AV1: How would you rate the speed of resolution given to problems that occur?1 | AW1: How would you rate the supplier initiative to take mitigation/preventive action to prevent the problem from recurring?1 | AX1: How would you rate supplier compliance with administrative processes, including completion of draft cooperation contract?2 | AY1: How would you rate The goods/services provided by the Supplier against the agreed standards | AZ1: How would you rate the supplier's services? | BA1: How would you rate the supplier's service in providing a guarantee of administrative services for archive management, computer data collection for all AXA cartons, and ease of access for AXA to the ar | BB1: How would you rate the supplier's service in providing the required number of empty cartons? | BC1: How would you rate overall quality of the work reports provided by the Supplier?2 | BD1: How would you rate the completeness report containing the number of AXA cartons deposited in the supplier's warehouse, a list of cartons that are being borrowed (retrieval) and have not been returned | BE1: How would you rate the solutions provided when there is trouble?2 | BF1: How would you rate the resolution to the problem that occurred?2 | BG1: How would you rate the speed of resolution given to problems that occur?2 | BH1: How would you rate the supplier initiative to take mitigation/preventive action to prevent the problem from recurring?2 | BI1: How would you rate supplier compliance with administrative processes, including completion of draft cooperation contract?3 | BJ1: How would you rate the goods/services provided by the Supplier against the agreed standards1 | BK1: How would you rate overall quality of the work reports provided by the Supplier?3 | BL1: How would you rate the solutions provided when there is trouble?3 | BM1: How would you rate the resolution to the problem that occurred?3 | BN1: How would you rate the supplier initiative to take mitigation/preventive action to prevent the problem from recurring?3 | BO1: How would you rate the accuracy of the data in the Supplier's reports?2 | BP1: How would you rate the overall quality of the work reports provided by the Supplier? | BQ1: How would you rate the competence of people provided by the supplier to provide support (understand AXITS and/or DMTM software)? | BR1: How would you rate the supplier support in providing the form of consultation, offsite and onsite support if there is a disruption to application operations? | BS1: How would you rate the supplier support in doing periodic checks once every 3 months to maintain application quality, including application performance checks (profiling) and error log checks? | BT1: How would you rate the supplier support for updating versions of components, frameworks and libraries issued by third parties with prior written approval from AXA if this is possible? | BU1: How would you rate the suppliers support in compliance to security? | BV1: How would you rate the supplier initiative to take mitigation/preventive action to prevent the problem from recurring?4 | BW1: How would you rate supplier compliance with administrative processes, including completion of draft cooperation contract?4 | BX1: How would you rate the goods/services provided by the Supplier against the agreed standards2 | BY1: How would you rate the Customer Interaction Requirement which includes: | BZ1: How would you rate the Case Management which includes: | CA1: How would you rate the Integration process which includes: | CB1: How would you rate the Architectural Requirement? | CC1: How would you rate the Security Requirement? | CD1: How would you rate the Backup and Restore, Capacity and Performance Requirements? | CE1: How would you rate the Operational and Configuration Management? | CF1: How would you rate the accuracy of the data in the Supplier's reports?3 | CG1: How would you rate overall quality of the work reports provided by the Supplier?4 | CH1: How would you rate the solutions provided when there is trouble?4 | CI1: How would you rate the resolution to the problem that occurred?4 | CJ1: How would you rate the speed of resolution given to problems that occur?3 | CK1: How would you rate the supplier initiative to take mitigation/preventive action to prevent the problem from recurring?5 | CL1: How would you rate supplier compliance with administrative processes, including completion of draft cooperation contract?5 | CM1: How would you rate the accuracy of the data in the Supplier's reports?4 | CN1: How would you rate the overall quality of the work reports provided by the Supplier?1 | CO1: How would you rate the performing installation, setup and configuration of 3Dolphins? | CP1: How would you rate the integration of 3Dolphins with SalesForce? | CQ1: How would you rate the Chatbot Corpus with data provided by AXA? | CR1: How would you rate the supplier's services in providing 3Dolphins Solutions as stated in the Functional Specification Document (FSD) and Technical Specification Document (TSD)? | CS1: How would you rate the supplier's services in conducting System Integration Test (SIT) with AXA IT testing team and IT Project Team? | CT1: How would you rate the supplier's services in conducting User Acceptance Test (UAT) with AXA Business Team and Project IT Team? | CU1: How would you rate the supplier's services in migrating to production server or Go Live and providing support after Go Live? | CV1: How would you rate the supplier's services in providing the human resources needed in the project and timeline according to the agreed scope? | CW1: How would you rate the supplier's services in assigning a Project Manager to coordinate with the AXA team? | CX1: How would you rate the supplier's project documentation as follows: | CY1: How would you rate the supplier support in providing the perform maintenance on all software related to 3Dolphins, which is installed in the AXA data center? | CZ1: How would you rate the supplier support in providing 3Dolphins application maintenance service time, namely 24 hours x 7 days a week, 365 days/year? | DA1: How would you rate the supplier support in preparing at least 2 people who understand and are experts in chatbots owned by AXA and can also provide support for services that often occur (eg. New custo | DB1: How would you rate the supplier support in providing support center that can be visited during AXA business hours to respond to any questions and issues that arise? | DC1: How would you rate the supplier support in providing SLA reports to AXA? | DD1: How would you rate the supplier support in providing testing and updates the Chatbot Solution if there is a new software version/release/patch according to the required conditions? | DE1: How would you rate the supplier support in reinstall the 3Dolphins application a maximum of 1 time per year if AXA will upgrade the hardware? | DF1: How would you rate the supplier support in providing a checklist to monitor daily activities? | DG1: How would you rate the supplier support in providing a testing configuration and event logging? | DH1: How would you rate the supplier support in providing a backup for short and long term? | DI1: How would you rate the goods/services provided by the Supplier against the agreed standards3 | DJ1: How would you rate the accuracy of the data in the Supplier's reports?5 | DK1: How would you rate overall quality of the work reports provided by the Supplier?5 | DL1: How would you rate the solutions provided when there is trouble?5 | DM1: How would you rate the resolution to the problem that occurred?5 | DN1: How would you rate the speed of resolution given to problems that occur | DO1: How would you rate the supplier initiative to take mitigation/preventive action to prevent the problem from recurring?6 | DP1: How would you rate supplier compliance with administrative processes, including completion of draft cooperation contract?6 | DQ1: How would you rate the shipping target achievement? | DR1: How would you rate the delivery times? Based on SLA, the delivery time are Monday to Saturday, service levels will remain the same from Monday to Friday. | DS1: How would you rate the Receipt retention period? | DT1: How would you rate the Airway Bill Storage: | DU1: How would you rate the Handling of Policies/Documents and/or delivery process? | DV1: How would you rate the response to complaints/investigations of the delivery process? | DW1: How would you rate the response taken when a delivery failure occurs? | DX1: How would you rate the goods/services provided by the Supplier against the agreed standards?1 | DY1: How would you rate the accuracy of the data in the Supplier's reports?6 | DZ1: How would you rate overall quality of the work reports provided by the Supplier?6 | EA1: How would you rate the solutions provided when there is trouble?6 | EB1: How would you rate the resolution to the problem that occurred?6 | EC1: How would you rate the supplier initiative to take mitigation/preventive action to prevent the problem from recurring?7 | ED1: How would you rate the service provided? | EE1: How would you rate the Complaint Handling? | EF1: How would you rate the service provided?1 | EG1: How would you rate the accuracy of the data in the Supplier's reports?7 | EH1: How would you rate overall quality of the work reports provided by the Supplier?7 | EI1: How would you rate the solutions provided when there is trouble?7 | EJ1: How would you rate the resolution to the problem that occurred?7 | EK1: How would you rate the supplier initiative to take mitigation/preventive action to prevent the problem from recurring?8 | EL1: How would you rate supplier compliance with administrative processes, including completion of draft cooperation contract?7 | EM1: How would you rate the goods/services provided by the Supplier against the agreed standards?2 | EN1: How would you rate overall quality of the work reports provided by the Supplier?8 | EO1: How would you rate the solutions provided when there is trouble?8 | EP1: How would you rate the speed of resolution given to problems that occur?4 | EQ1: How would you rate the Vendor initiative to take mitigation/preventive action to prevent the problem from recurring? | ER1: How would you rate supplier compliance with administrative processes, including completion of draft cooperation contract? | ES1: How would you rate supplier ability to provide manpower according to the required position and job description before the project starts? | ET1: How would you rate the Supplier’s Timelines in replacing manpower? | EU1: How would you rate the Supplier’s ability to conduct training for TSO? | EV1: How would you rate the Supplier’s ability to conduct training for Leader? | EW1: How would you rate the Supplier’s ability to conduct training for Manager? | EX1: How would you rate the Supplier’s ability to ensure employees achieve an A rating on the KPI Dashboard for 3 consecutive months to qualify for promotion? | EY1: How would you rate the Supplier’s ability to enforce demotion for employees who receive a D rating for 3 consecutive months? | EZ1: How would you rate the Supplier’s ability to provide accurate and complete data management as per agreed requirements which is providing leads, mapping, until distribute to TSO? | FA1: How would you rate the Supplier’s ability to ensure connectivity between the telemarketing system and our back end (DMTM) system? | FB1: How would you rate the Supplier’s ability to recommend suitable premise locations and provide photos as required? | FC1: How would you rate the Supplier’s ability to develop and execute Sales Activity & Monitoring which include: | FD1: How would you rate the Technical services that is used to penetrate the application which includes: 1. Technical Specification Design. 2. Hardware and capacity sizing for concurrent requests 3. Functi | FE1: How would you rate the after sales support capability and methodology? | FF1: How would you rate the availability of documentation for service (user manual, troubleshoot document, setup document, etc)? | FG1: How would you rate the Technical services that is used to penetrate the application which includes: 1. Technical Specification Design. 2. Hardware and capacity sizing for concurrent requests 3. Functi1 | FH1: How would you rate the after sales support capability and methodology?1 | FI1: How would you rate the availability of documentation for product (user manual, troubleshoot document, setup document, etc)? | FJ1: How would you rate the Technical services that is used to penetrate the application which includes: 1. Technical Specification Design. 2. Hardware and capacity sizing for concurrent requests 3. Functi2 | FK1: How would you rate the after sales support capability and methodology?2 | FL1: How would you rate the availability of documentation for product (user manual, troubleshoot document, setup document, etc)?1 | FM1: How would you rate the Supplier’s ability to implement the backup plan within 3 hours after system downtime occurs? | FN1: How would you rate the supplier's timeliness in delivering goods/services compared to the agreed-upon timeline? | FO1: How would you rate the supplier's timeliness in sending reports to you? | FP1: How would you rate the supplier's speed ​​of administrative completion, including completion of contracts draft? | FQ1: How would you rate the supplier's timeliness in delivering goods/services compared to the agreed-upon timeline?1 | FR1: How would you rate the supplier's timeliness in sending reports to you? | FS1: How would you rate the supplier's Traffic Confirmation SLA Fulfillment? | FT1: How would you rate the supplier's speed ​​of administrative completion, including completion of contracts draft? | FU1: How would you rate the supplier's timeliness in delivering goods/services compared to the agreed-upon timeline?2 | FV1: How would you rate the supplier's timeliness in sending reports to you? Based on SLA, suppliers must provide reports on the 10th of each month. | FW1: How would you rate the supplier's speed ​​of administrative completion, including completion of contracts draft? 1 | FX1: How would you rate the supplier's SLA Fulfillment? | FY1: How would you rate the Supplier's timeliness in delivering goods/services compared to the agreed-upon timeline?3 | FZ1: How would you reat timeliness of the work reports submitted by the Supplier to you? | GA1: How would you rate the supplier's timeliness in sending reports to you? Based on SLA, support reports should be sent every 3 months on the 10th | GB1: How would you rate the supplier's speed ​​of administrative completion, including completion of contracts draft?1 | GC1: How would you rate the supplier's response time? | GD1: How would you rate the supplier's resolution time? | GE1: How would you rate the supplier's timeliness in delivering goods/services compared to the agreed-upon timeline?4 | GF1: How would you rate the supplier's timeliness in sending reports to you?1 | GG1: How would you rate the supplier's speed ​​of administrative completion, including completion of contracts draft?2 | GH1: How would you rate the supplier's communication with you? | GI1: How would you rate the supplier's PIC's availability to be contacted when needed? | GJ1: How would you rate the supplier's response speed to you when there are issues? | GK1: Has the vendor completed the latest Financial Assessment? | GL1: Has the vendor’s Reputational Assessment been performed? | GM1: Does the services require the fulfillment of Data Privacy Impact Assessment (DPIA)? | GN1: Does the services require the fulfillment of Data Privacy Service Provider Questionnaire assessment (DPSQ)? | GO1: Does the services require the fulfillment of Vendor Security Due Diligence Tooling (VSDDT)? | GP1: Has the Vendor Security Due Diligence Tooling (VSDDT) been completed and approved? | GQ1: Based on the the results (financial, reputational, DPIA, VSDDT, DPSQ), do you have an action plan in place? If yes, has it been completed, and have you coordinated with the relevant SMEs? | GR1: Have all required actions been completed by your team? | GS1: Please provide feedback or suggestion for the supplier, including areas for improvement
A2: 46112.432 | B2: 46112.436 | C2: fauzi.aryanto@axa-mandiri.co.id | D2: Fauzi ARYANTO | E2: Fauzi Aryanto | F2: Itsec Asia - Penetration Testing | FJ2: 3 | FK2: 3 | FL2: 3 | FN2: 3 | FO2: 3 | FP2: 3 | GH2: 3 | GI2: 3 | GJ2: 3 | GK2: Yes | GL2: Yes | GM2: Not required – DPIA is not applicable for this service | GN2: Not required – DPSQ is not applicable for this service | GO2: Required – VSDDT completed and approved | GQ2: Yes – All action items have been completed and coordinated with relevant SME | GS2: Currently no need improvement
A3: 46112.436 | B3: 46112.437 | C3: fauzi.aryanto@axa-mandiri.co.id | D3: Fauzi ARYANTO | E3: Fauzi Aryanto | F3: Iproteksi Telematika - Penetration Testing | FG3: 4 | FH3: 4 | FI3: 4 | FN3: 4 | FO3: 4 | FP3: 4 | GH3: 4 | GI3: 4 | GJ3: 4 | GK3: Yes | GL3: Yes | GM3: Not required – DPIA is not applicable for this service | GN3: Not required – DPSQ is not applicable for this service | GO3: Required – VSDDT completed and approved | GQ3: Yes – All action items have been completed and coordinated with relevant SME | GS3: no need improvement
A4: 46112.437 | B4: 46112.438 | C4: fauzi.aryanto@axa-mandiri.co.id | D4: Fauzi ARYANTO | E4: Fauzi Aryanto | F4: FPT Metrodata - Penetration Testing | FD4: 3 | FE4: 3 | FF4: 3 | FN4: 3 | FO4: 3 | FP4: 3 | GH4: 3 | GI4: 3 | GJ4: 3 | GK4: Yes | GL4: Yes | GM4: Not required – DPIA is not applicable for this service | GN4: Not required – DPSQ is not applicable for this service | GO4: Required – VSDDT completed and approved | GQ4: Yes – All action items have been completed and coordinated with relevant SME | GS4: No need improvement
A5: 46112.552 | B5: 46112.566 | C5: ibnu.kumala@axa-mandiri.co.id | D5: Ibnu KUMALA | E5: ibnu kumala | F5: Satria Antaran Prima - Mailing Room | DX5: 3 | DY5: 4 | DZ5: 3 | EA5: 3 | EB5: 3 | EC5: 3 | ED5: 4 | EE5: 3 | FN5: 3 | FO5: 4 | FP5: 3 | GH5: 4 | GI5: 4 | GJ5: 3 | GK5: Yes | GL5: Yes | GM5: Required – DPIA completed and approved | GN5: Not required – DPSQ is not applicable for this service | GO5: Required – VSDDT completed and approved | GQ5: Yes – All action items have been completed and coordinated with relevant SME | GS5: Over all mailing ok, please improve coordinated with Headoffice team for reduce complain/misscomm (ex case overseas shipment )
A6: 46112.572 | B6: 46112.588 | C6: fifin.sarinurlita@axa-mandiri.co.id | D6: Fifin SARINURLITA | E6: fifin sarinurlita | F6: Informasi Teknologi Indonesia - SMS Broadcast | AA6: 3 | AB6: 3 | AC6: 3 | AD6: 3 | AE6: 3 | AF6: 3 | AG6: 3 | AH6: 3 | AI6: 3 | AJ6: 3 | AK6: 3 | FQ6: 3 | FR6: 3 | FS6: 3 | FT6: 3 | GH6: 3 | GI6: 3 | GJ6: 3 | GK6: Yes | GL6: Yes | GM6: Required – DPIA completed and approved | GN6: Required – DPSQ completed and approved | GO6: Required – VSDDT completed and approved | GQ6: No – No action items were required | GS6: Jatis has provided good service throughout this year
A7: 46112.614 | B7: 46112.614 | C7: fifin.sarinurlita@axa-mandiri.co.id | D7: Fifin SARINURLITA | E7: fifin sarinurlita | F7: Satria Antaran Prima - Courier Service | DI7: 3 | DJ7: 3 | DK7: 3 | DL7: 3 | DM7: 3 | DN7: 3 | DO7: 3 | DP7: 3 | DQ7: 3 | DR7: 3 | DS7: 3 | DT7: 3 | DU7: 3 | DV7: 3 | DW7: 3 | GE7: 3 | GF7: 3 | GG7: 3 | GH7: 3 | GI7: 3 | GJ7: 3 | GK7: Yes | GL7: Yes | GM7: Required – DPIA completed and approved | GN7: Required – DPSQ completed and approved | GO7: Required – VSDDT completed and approved | GQ7: Yes – Action items identified, but follow‑up and coordination with relevant SME is still required | GS7: SAP has provided excellent service throughout this year
A8: 46112.639 | B8: 46112.645 | C8: ibnu.kumala@axa-mandiri.co.id | D8: Ibnu KUMALA | E8: ibnu kumala | F8: Multifiling Mitra Indonesia - Record Management Service | AY8: 3 | AZ8: 3 | BA8: 3 | BB8: 3 | BC8: 3 | BD8: 4 | BE8: 3 | BF8: 3 | BG8: 3 | BH8: 3 | BI8: 3 | FU8: 3 | FV8: 3 | FW8: 3 | FX8: 3 | GH8: 3 | GI8: 3 | GJ8: 3 | GK8: Yes | GL8: Yes | GM8: Required – DPIA completed and approved | GN8: Required – DPSQ completed and approved | GO8: Required – VSDDT completed and approved | GQ8: Yes – All action items have been completed and coordinated with relevant SME | GS8: impprove innovation dan simplyfy process
A9: 46112.736 | B9: 46112.749 | C9: nuril.hudha@axa-mandiri.co.id | D9: Nuril HUDHA | E9: Nuril Hudha | F9: Indosat - Layanan PBX berbasiskan cloud dengan Teknologi SIP Trunk | G9: 4 | H9: 3 | I9: 3 | J9: 3 | K9: 3 | L9: 3 | M9: 3 | N9: 3 | O9: 3 | P9: 3 | Q9: 3 | R9: 3 | S9: 3 | T9: 3 | U9: 3 | V9: 3 | X9: 3 | Y9: 3 | Z9: 3 | FN9: 3 | FO9: 3 | FP9: 3 | GH9: 4 | GI9: 4 | GJ9: 4 | GK9: No | GL9: Yes | GM9: Required – DPIA completed and approved | GN9: Not required – DPSQ is not applicable for this service | GO9: Required – VSDDT completed and approved | GQ9: Yes – Action items identified, but follow‑up and coordination with relevant SME is still required | GS9: The performance is getting better, please keep improve the performance.
A10: 46113.576 | B10: 46113.58 | C10: raninta.mahardi@axa-mandiri.co.id | D10: Raninta MAHARDI | E10: Raninta Mahardi | F10: Ciptadra Softindo - Pemeliharaan Axits & DMTM | BJ10: 4 | BK10: 4 | BL10: 4 | BM10: 4 | BN10: 4 | BO10: 4 | BP10: 4 | BQ10: 4 | BR10: 4 | BS10: 4 | BT10: 4 | BU10: 4 | BV10: 4 | BW10: 4 | FY10: 4 | FZ10: 4 | GA10: 4 | GB10: 4 | GC10: 4 | GD10: 4 | GH10: 4 | GI10: 4 | GJ10: 4 | GK10: Yes | GL10: Yes | GM10: Required – DPIA completed and approved | GN10: Required – DPSQ completed and approved | GO10: Required – VSDDT completed and approved | GQ10: Yes – All action items have been completed and coordinated with relevant SME | GS10: Performance is Good
A11: 46114.442 | B11: 46114.443 | C11: bella.depari@axa-mandiri.co.id | D11: Bella Friska DEPARI | E11: Bella Friska Depari | F11: Target Sukses Sinergi - Email Marketing Automation | EF11: 3 | EG11: 3 | EH11: 4 | EI11: 4 | EJ11: 4 | EK11: 4 | EL11: 4 | FN11: 4 | FO11: 4 | FP11: 4 | GH11: 4 | GI11: 4 | GJ11: 4 | GK11: Yes | GL11: Yes | GM11: Required – DPIA completed and approved | GN11: Required – DPSQ completed and approved | GO11: Required – VSDDT completed and approved | GQ11: Yes – All action items have been completed and coordinated with relevant SME | GS11: Harganya buat next contrac please murahin ya
A12: 46114.447 | B12: 46114.47 | C12: djoko.djoko@axa-mandiri.co.id | D12: Djoko DJOKO | E12: DJOKO | F12: Inmotion Inovasi Teknologi - Jasa Aplikasi Chatbot dan Live Chat | BX12: 4 | BY12: 4 | BZ12: 4 | CA12: 4 | CB12: 4 | CC12: 4 | CD12: 4 | CE12: 4 | CF12: 4 | CG12: 4 | CH12: 4 | CI12: 4 | CJ12: 4 | CK12: 4 | CL12: 4 | CM12: 4 | CN12: 4 | CO12: 4 | CP12: 4 | CQ12: 4 | CR12: 4 | CS12: 4 | CT12: 4 | CU12: 4 | CV12: 4 | CW12: 4 | CX12: 4 | CY12: 4 | CZ12: 4 | DA12: 4 | DB12: 4 | DC12: 4 | DD12: 4 | DE12: 4 | DF12: 4 | DG12: 4 | DH12: 4 | FN12: 4 | FO12: 4 | FP12: 4 | GH12: 4 | GI12: 4 | GJ12: 4 | GK12: Yes | GL12: Yes | GM12: Required – DPIA completed and approved | GN12: Required – DPSQ not yet completed or approved | GO12: Required – VSDDT completed and approved | GQ12: Yes – All action items have been completed and coordinated with relevant SME | GS12: continue performing thorough and frequent periodic checks to ensure that during service hours, there are no issues that could disrupt operations and resolve the remaining unresolved 401 issue Berikan umpan balik Anda tentang BizChat
A13: 46121.649 | B13: 46121.649 | C13: chandra.putra@axa-mandiri.co.id | D13: Chandra Nugraha PUTRA | E13: Chandra Nugraha Putra | F13: Mitra Integrasi Informatika - SFDC Maintenance | AL13: 5 | AM13: 5 | AN13: 5 | AO13: 4 | AP13: 5 | AQ13: 5 | AR13: 5 | AS13: 5 | AT13: 5 | AU13: 5 | AV13: 4 | AW13: 5 | AX13: 5 | FN13: 4 | FO13: 5 | FP13: 5 | GH13: 5 | GI13: 5 | GJ13: 5 | GK13: No | GL13: No | GM13: Not required – DPIA is not applicable for this service | GN13: Not required – DPSQ is not applicable for this service | GO13: Required – VSDDT not yet completed or approved | GQ13: No – No action items were required | GS13: verall, the level of support has been satisfactory. The improvements carried out were highly effective, and several demands were consistent with the initial assessment and expectations.

Sheet RAW DATA Q1 - 2
A1: Start time | B1: Completion time | C1: Email | D1: Name | E1: User Name | F1: Supplier and Service | G1: How would you rate the services provided by the supplier? | H1: How would you rate the accuracy of the data in the Supplier's reports? | I1: How would you rate overall quality of the work reports provided by the Supplier | J1: How would you rate the solutions provided by the supplier when there is trouble? | K1: How would you rate the resolution to the problem that occurred? | L1: How would you rate the speed of resolution given to problems that occur? | M1: How would you rate supplier initiative to take mitigation/preventive action to prevent recurring problem? | N1: How would you rate supplier compliance with administrative processes, including completion of draft cooperation contract? | O1: How would you rate the goods/services provided by the Supplier against the agreed standards | P1: How would you rate the accuracy of the data in the Supplier's reports? | Q1: How would you rate overall quality of the work reports provided by the Supplier? | R1: How would you rate the solutions provided when there is trouble? | S1: How would you rate the Vendor initiative to take mitigation/preventive action to prevent the problem from recurring? | T1: How would you rate supplier compliance with administrative processes, including completion of draft cooperation contract?1 | U1: How would you rate the supplier implementation on a Project Management Approach, which includes: | V1: How would you rate the supplier support in providing 1 (one) Technical Support personnel who is specifically assigned? Based on SLA, this technical support will be assigned at Menara Global and Graha | W1: How would you rate the supplier support in providing technical support personnel who will perform several activities such as: | X1: How would you rate the supplier support in maintaining 99% SLA for System Availability in providing the Services to AMFS (SLA calculation does not include service downtime triggered by deliverables no | Y1: How would you rate the supplier support in providing Annual Support such as: | Z1: How would you rate services provided by the Supplier against the agreed standards | AA1: How would you rate the services provided by the Supplier which should include: | AB1: How would you rate the supplier's accuracy of the data in the Supplier's reports? | AC1: How would you rate the overall quality of the work reports provided by the Supplier? | AD1: How would you rate the solutions provided when there is trouble?1 | AE1: How would you rate the vendor initiative to take mitigation/preventive action to prevent the problem from recurring?1 | AF1: How would you rate supplier compliance with administrative processes, including completion of draft cooperation contract?2 | AG1: How would you rate the supplier services in carrying out maintenance including repairs to the Common Areas and all other areas of the office not mentioned in the Lease, including electrical systems, a | AH1: How would you rate the supplier services in make repairs to: | AI1: How would you rate the services provided by the Supplier against the agreed standards | AJ1: How would you rate the accuracy of the data in the Supplier's reports?1 | AK1: How would you rate overall quality of the work reports provided by the Supplier?1 | AL1: How would you rate the solutions provided when there is trouble?2 | AM1: How would you rate the vendor initiative to take mitigation/preventive action to prevent the problem from recurring?2 | AN1: How would you rate supplier compliance with administrative processes, including completion of draft cooperation contract?3 | AO1: How would you rate the supplier's service in providing training materials in accordance with: | AP1: How would you rate the supplier's service in creating a discussion session that covers current conditions, understanding objectives, and discussions using specific cases from the training material wit | AQ1: How would you rate the supplier's service in conducting 1 (one) session of Data Privacy and Protection awareness training sessions for AXA and its related business units, along with a post-test. | AR1: How would you rate the supplier's response time for service issues? | AS1: How would you rate the supplier's project management & management report? | AT1: How would you rate the goods/services provided by the Supplier against the agreed standards1 | AU1: How would you rate the accuracy of the data in the Supplier's reports?2 | AV1: How would you rate the Vendor initiative to take mitigation/preventive action to prevent the problem from recurring?3 | AW1: How would you rate supplier compliance with administrative processes, including completion of draft cooperation contract?4 | AX1: How would you rate the Installation of SAS IFRS17 solution on AXA infrastructure? | AY1: How would you rate the workshops and finalize functional specification documents that summarize requirements which conducted by the supplier? | AZ1: How would you rate the implementation of an end-to-end solution flow design for SAS IFRS17? | BA1: How would you rate the Implementation of SAS IFRS17solution? | BB1: How would you rate the End-to-End Calculation Functions which includes: | BC1: How would you rate the PSAK74 Contract Grouping using Data Input and Predefine Rule which generates: | BD1: How would you rate PSAK74 System implementation on its standard and configurable rule which includes: | BE1: How would you rate the currencies and interest rate facilitation? | BF1: How would you rate the capability to estimate the Initial Recognition? | BG1: How would you rate the capability to estimate GMM/PAA/VFA Approach both direct and reinsurance: | BH1: How would you rate the capability to do the Allocation on Actual Cash Flow (CF): | BI1: How would you rate the capability to generate PSAK74 Disclosure in monthly base: | BJ1: How would you rate the System Availability, Redundancy, and Overload Protection? | BK1: How would you rate the Common Security Access? | BL1: How would you rate the Audit Trail? | BM1: How would you rate the supplier's service in providing one month warranty support after go-live? | BN1: How would you rate the supplier's services in conducting three-day user training for SAS IFRS17 solution and conducted one-day system administration training for users? | BO1: How would you rate the services provided by the Supplier against the agreed standards1 | BP1: How would you rate overall quality of the work reports provided by the Supplier?2 | BQ1: How would you rate the solutions provided when there is trouble?3 | BR1: How would you rate the speed of resolution given to problems that occur?1 | BS1: How would you rate the Vendor initiative to take mitigation/preventive action to prevent the problem from recurring?4 | BT1: How would you rate supplier compliance with administrative processes, including completion of draft cooperation contract?5 | BU1: How would you rate the implementation and integration with surrounding systems? | BV1: How would you rate the supplier provides testing before the project is carried out? | BW1: How would you rate the technical Documentation includes Specifications and Design, Testing, Operational Documents, Administration, and Maintenance Guide, Installation from scratch, and Tuning Guide? | BX1: How would you rate the Supplier’s ability to deliver monthly Payroll Services? | BY1: How would you rate the Supplier’s ability to deliver Cash Management Services, including the following aspects: | BZ1: How would you rate the Supplier’s ability to deliver Compliance Services, including the following aspects: | CA1: How would you rate the Supplier’s ability to deliver BPJS Kesehatan Services? | CB1: How would you rate the Supplier’s ability to comply with penalty provisions for payroll processing? | CC1: How would you rate the Supplier’s ability to execute the Special Project for BPJS Kesehatan? | CD1: How would you rate the Supplier’s ability to deliver Policy Printing Services SLA? | CE1: How would you rate the Supplier’s ability to deliver Letter Printing Services? | CF1: How would you rate the Supplier’s ability to deliver Training Material Document Printing? | CG1: How would you rate the Supplier’s ability to deliver DMC Service which includes: | CH1: How would you rate the Supplier’s ability to deliver DMC POS/Claim data and reporting, including the following aspects: | CI1: How would you rate the Supplier ability to do Data maintenance, data security, and access control? | CJ1: How would you rate the supplier's timeliness in delivering goods/services compared to the agreed-upon timeline? | CK1: How would you rate the supplier's timeliness in sending reports to you? | CL1: How would you rate the supplier's speed ​​of administrative completion, including completion of contracts draft? | CM1: How would you rate the supplier's timeliness in delivering goods/services compared to the agreed-upon timeline?1 | CN1: How would you rate the supplier's timeliness in sending reports to you?1 | CO1: How would you rate the supplier's speed ​​of administrative completion, including completion of contracts draft?1 | CP1: How would you rate the Supplier’s ability to meet payroll disbursement timelines? | CQ1: How would you rate the Supplier’s ability to meet the timelines for report and form submissions, including the following aspects: | CR1: How would you rate the Supplier’s ability to meet the required timelines for payment processing? | CS1: How would you rate the supplier's communication with you? | CT1: How would you rate the supplier's PIC's availability to be contacted when needed? | CU1: How would you rate the supplier's response speed to you when there are issues? | CV1: Has the vendor completed the latest Financial Assessment? | CW1: Has the vendor’s Reputational Assessment been completed? | CX1: Does the services require the fulfillment of Data Privacy Impact Assessment (DPIA)? | CY1: Has the Data Privacy Impact Assessment (DPIA) been completed and approved? | CZ1: Does the services require the fulfillment of Data Privacy Service Provider Questionnaire assessment (DPSQ)? | DA1: Has the Data Privacy Service Provider Questionnaire Assessment (DPSQ) been completed and approved? | DB1: Does the services require the fulfillment of Vendor Security Due Diligence Tooling (VSDDT)? | DC1: Has the Vendor Security Due Diligence Tooling (VSDDT) been completed and approved? | DD1: Based on the the results (financial, reputational, DPIA, VSDDT, DPSQ), do you have an action plan in place? If yes, has it been completed, and have you coordinated with the relevant SMEs? | DE1: Have all required actions been completed by your team? | DF1: Please provide feedback or suggestion for the supplier, including areas for improvement
A2: 46111.576 | B2: 46111.583 | C2: andreas.boedijanto@axa-mandiri.co.id | D2: Andreas ANDREAS | E2: Andreas | F2: Sutra Management Consultancies - Implementasi SAS IFRS17 | AT2: 4 | AU2: 4 | AV2: 4 | AW2: 4 | AX2: 4 | AY2: 3 | AZ2: 3 | BA2: 3 | BB2: 3 | BC2: 4 | BD2: 4 | BE2: 3 | BF2: 3 | BG2: 3 | BH2: 4 | BI2: 4 | BJ2: 3 | BK2: 3 | BL2: 3 | BM2: 3 | BN2: 3 | CJ2: 3 | CK2: 4 | CL2: 4 | CS2: 4 | CT2: 4 | CU2: 4 | CV2: Yes | CW2: Yes | CX2: Not required – DPIA is not applicable for this service | CZ2: Not required – DPSQ is not applicable for this service | DB2: Required – VSDDT completed and approved | DD2: Yes – Action items identified, but follow‑up and coordination with relevant SME is still required | DF2: Local vendor Sutra is affiliated with SAS Technology which is known as more expensive system compared to other vendors during the Vendor Bidding Process. However, SAS Technology System has been used in few well-known insurance companies in Indonesia, so it is easier to get the review and information; mostly positive.
A3: 46111.626 | B3: 46111.635 | C3: yulia.kurniati@axa-mandiri.co.id | D3: Yulia KURNIATI | E3: Yulia Kurniati | F3: Reycom Document Solution - Printing & Data Management Center | CD3: 4 | CE3: 4 | CF3: 3 | CG3: 5 | CH3: 5 | CI3: 5 | CM3: 5 | CN3: 5 | CO3: 5 | CS3: 5 | CT3: 5 | CU3: 5 | CV3: Yes | CW3: Yes | CX3: Required – DPIA completed and approved | CZ3: Required – DPSQ completed and approved | DB3: Required – VSDDT completed and approved | DD3: No – No action items were required | DF3: More inovation for 2026
A4: 46112.644 | B4: 46112.648 | C4: ibnu.kumala@axa-mandiri.co.id | D4: Ibnu KUMALA | E4: ibnu kumala | F4: Arah Sejahtera Abadi - Perjanjian Sewa Menyewa | Z4: 3 | AA4: 3 | AB4: 3 | AC4: 3 | AD4: 3 | AE4: 3 | AF4: 3 | AG4: 2 | AH4: 3 | CJ4: 3 | CK4: 3 | CL4: 3 | CS4: 3 | CT4: 3 | CU4: 3 | CV4: No | CW4: No | CX4: Not required – DPIA is not applicable for this service | CZ4: Not required – DPSQ is not applicable for this service | DB4: Not required – VSDDT is not applicable for this service | DD4: No – No action items were required | DF4: Improve quality service, specially for leakage,
A5: 46112.694 | B5: 46112.699 | C5: sony.nugroho@axa-mandiri.co.id | D5: Sony NUGROHO | E5: Sony Nugroho | F5: Deloitte Consulting - Data Privacy & Pelatihan Personal Data Protection (PDP) | AI5: 3 | AJ5: 3 | AK5: 3 | AL5: 3 | AM5: 3 | AN5: 3 | AO5: 3 | AP5: 4 | AQ5: 4 | AR5: 3 | AS5: 3 | CJ5: 3 | CK5: 3 | CL5: 3 | CS5: 3 | CT5: 4 | CU5: 3 | CV5: Yes | CW5: Yes | CX5: Required – DPIA completed and approved | DB5: Required – VSDDT completed and approved | DD5: No – No action items were required | DF5: Need more improvement regarding initiative to take mitigation/preventive action to prevent the problem from recurring/current issue.
A6: 46113.349 | B6: 46113.352 | C6: enung.haryati@axa-mandiri.co.id | D6: Enung HARYATI | E6: Enung Haryati | F6: TMF Indonesia - Payroll | BX6: 3 | BY6: 3 | BZ6: 3 | CA6: 3 | CB6: 3 | CC6: 3 | CP6: 3 | CQ6: 3 | CR6: 3 | CS6: 3 | CT6: 3 | CU6: 3 | DF6: Always check and recheck the task in internal PIC TMF before send the report to AMFS PIC
A7: 46114.564 | B7: 46114.572 | C7: reza.resdilana@axa-mandiri.co.id | D7: Reza RESDILANA | E7: Reza Resdilana | F7: Karya Putra Surya Gemilang - Telemarketing Revamp Project | O7: 3 | P7: 3 | Q7: 3 | R7: 3 | S7: 3 | T7: 3 | U7: 4 | V7: 3 | W7: 3 | X7: 3 | Y7: 3 | CJ7: 3 | CK7: 3 | CL7: 3 | CS7: 3 | CT7: 3 | CU7: 3 | CV7: Yes | CW7: Yes | CX7: Required – DPIA completed and approved | CZ7: Required – DPSQ not yet completed or approved | DB7: Required – VSDDT completed and approved | DD7: Yes – All action items have been completed and coordinated with relevant SME | DF7: Diharapkan untuk tim project yang diassign apabila CR sudah di signoff agar availibility dari resource ready
